Workbook

Sheet Index
C4: Finance Analysis 2017- 2024 (7.6 years)
D6: 7.6 years historical analysis & projections
D7: TABLE OF CONTENTS
D10: Note: Click on below subject and it will take you direct to the worksheet
D12: 1.Financial Statements | I12: Complete
D14: 2.EBITDA | I14: Complete
D16: 3.FS with Footnotes adjusted (Detailed) | I16: Complete
D18: 4.Important Note | I18: Complete
D20: 5.Cash Flow Analysis (CFS) | I20: Complete
D22: 6.Free Cash Flow to Firm (FCFF) (Unlevered) | I22: Complete
D24: 7.Free Cash Flow to Equity (FCFE) (Levered) | I24: Complete
D26: 8.WACC / Terminal Value / Enterprise Value | I26: WACC Complete, Balance TV/EV
D28: 9.Financial Ratios | I28: Complete
D30: 10.Dashboard | I30: Complete
D32: 11.Resource | I32: Complete
D34: 12.Funds Flow Statement (WC 23 Vs 24) | I34: Complete
... D40: 14.Projections | I40: Balance

Sheet  - FS 
B1: Home Index (click here)
B3: Balance sheet check | C3: =IF(ABS(C44-C66)>1,"Error", "OK") -> OK | D3: =IF(ABS(D44-D66)>1,"Error", "OK") -> OK | E3: =IF(ABS(E44-E66)>1,"Error", "OK") -> OK | F3: =IF(ABS(F44-F66)>1,"Error", "OK") -> OK | G3: =IF(ABS(G44-G66)>1,"Error", "OK") -> OK | H3: =IF(ABS(H44-H66)>1,"Error", "OK") -> OK | I3: =IF(ABS(I44-I66)>1,"Error", "OK") -> OK | J3: =IF(ABS(J44-J66)>1,"Error", "OK") -> OK
B5: INCOME STATEMENT | C5: IFRS Yr | J5: 6 months
B7: In millions SAR | C7: 2017 | D7: =C7+1 -> 2018 | E7: =D7+1 -> 2019 | F7: =E7+1 -> 2020 | G7: =F7+1 -> 2021 | H7: =G7+1 -> 2022 | I7: =H7+1 -> 2023 | J7: =I7+1 -> 2024
B8: Revenues | C8: 618298747 | D8: 764562777 | E8: 646481189 | F8: 563272730 | G8: 791000421 | H8: 982392366 | I8: 657861400 | J8: 331615280
B9: (COGS) | C9: -591964630 | D9: -598777348 | E9: -549474068 | F9: -509029689 | G9: -597406509 | H9: -634195731 | I9: -613777216 | J9: -297601757
B10: Gross Profit | C10: =C8+C9 -> 26334117 | D10: =D8+D9 -> 165785429 | E10: =E8+E9 -> 97007121 | F10: =F8+F9 -> 54243041 | G10: =G8+G9 -> 193593912 | H10: =H8+H9 -> 348196635 | I10: =I8+I9 -> 44084184 | J10: =J8+J9 -> 34013523
B11: (General & Administrative Expenses) | C11: -29894040 | D11: -30645365 | E11: -35892355 | F11: -39295851 | G11: -23452169 | H11: -60358913 | I11: -75589414 | J11: -31732822
B12: (Selling & Distributions Expenses) | C12: -25721758 | D12: -27417941 | E12: -27872343 | F12: -28406133 | G12: -48153561 | H12: -27443025 | I12: -43953777 | J12: -16384038
B13: Operating Profit | C13: =C10+C11+C12 -> -29281681 | D13: =D10+D11+D12 -> 107722123 | E13: =E10+E11+E12 -> 33242423 | F13: =F10+F11+F12 -> -13458943 | G13: =G10+G11+G12 -> 121988182 | H13: =H10+H11+H12 -> 260394697 | I13: =I10+I11+I12 -> -75459007 | J13: =J10+J11+J12 -> -14103337
B14: Share in results of an associate company | C14: 2156928 | D14: 2275264 | E14: 2840173 | F14: 3145704 | G14: 2956531 | H14: 2843014 | I14: 2978122 | J14: 837337
B15: Reversal of expected credit losses | C15: -1200000 | D15: 0 | E15: 0 | F15: 0 | G15: 2344487 | H15: 0 | I15: 0 | J15: 0
B16: Other Income (net) | C16: 27344840 | D16: 1372852 | E16: 1623911 | F16: 869289 | G16: 1147654 | H16: 786773 | I16: -720365 | J16: 630152
B17: EBIT | C17: =C13+C14+C15+C16 -> -979913 | D17: =D13+D14+D15+D16 -> 111370239 | E17: =E13+E14+E15+E16 -> 37706507 | F17: =F13+F14+F15+F16 -> -9443950 | G17: =G13+G14+G15+G16 -> 128436854 | H17: =H13+H14+H15+H16 -> 264024484 | I17: =I13+I14+I15+I16 -> -73201250 | J17: =J13+J14+J15+J16 -> -12635848
B18: (Finance Cost) | C18: -33061003 | D18: -31560444 | E18: -34361598 | F18: -25380713 | G18: -20346696 | H18: -22607089 | I18: -34569636 | J18: -16226629
B19: (Zakat) | C19: -372338 | D19: -2294032 | E19: -653000 | F19: -801078 | G19: -2889609 | H19: -7973078 | I19: -356430 | J19: -421589
B20: Net Income | C20: =C17+C18+C19 -> -34413254 | D20: =D17+D18+D19 -> 77515763 | E20: =E17+E18+E19 -> 2691909 | F20: =F17+F18+F19 -> -35625741 | G20: =G17+G18+G19 -> 105200549 | H20: =H17+H18+H19 -> 233444317 | I20: =I17+I18+I19 -> -108127316 | J20: =J17+J18+J19 -> -29284066
B21: Remeasurement of Employee Defined Benefits | C21: -289452 | D21: -692696 | E21: 4070260 | F21: 439752 | G21: -2172110 | H21: -3994835 | I21: 2461410 | J21: 0
B22: Share of OCI (loss) of an associate | C22: 0 | D22: 0 | E22: 0 | F22: 0 | G22: -58985 | H22: -1653 | I22: -2292 | J22: 0
B23: Other Comprehensive Profit (Loss) for the year | C23: =C21+C22 -> -289452 | D23: =D21+D22 -> -692696 | E23: =E21+E22 -> 4070260 | F23: =F21+F22 -> 439752 | G23: =G21+G22 -> -2231095 | H23: =H21+H22 -> -3996488 | I23: =I21+I22 -> 2459118 | J23: =J21+J22 -> 0
B24: Total Comprehensive Income for Year . | C24: =C20+C21+C22 -> -34702706 | D24: =D20+D21+D22 -> 76823067 | E24: =E20+E21+E22 -> 6762169 | F24: =F20+F21+F22 -> -35185989 | G24: =G20+G21+G22 -> 102969454 | H24: =H20+H21+H22 -> 229447829 | I24: =I20+I21+I22 -> -105668198 | J24: =J20+J21+J22 -> -29284066
B25: Budgeted revenue | C25: 0 | D25: 0 | E25: 0 | F25: 0 | G25: 0 | H25: 0 | I25: 0 | J25: 0
B27: BALANCE SHEET | C27: IFRS Yr | J27: 6 months
B29: In millions SAR | C29: 2017 | D29: =C29+1 -> 2018 | E29: =D29+1 -> 2019 | F29: =E29+1 -> 2020 | G29: =F29+1 -> 2021 | H29: =G29+1 -> 2022 | I29: =H29+1 -> 2023 | J29: =I29+1 -> 2024
B30: Assets
B31: PP&E | C31: 849230150 | D31: 832826787 | E31: 794580526 | F31: 756950064 | G31: 691853720 | H31: 652194690 | I31: 643874701 | J31: 628232899
B32: Right of Use Assets | C32: 0 | D32: 0 | E32: 9564766 | F32: 9793474 | G32: 14929593 | H32: 12001937 | I32: 9766712 | J32: 16605522
B33: Intangible Assets | C33: 652930 | D33: 204417 | E33: 472836 | F33: 432405 | G33: 305325 | H33: 1123205 | I33: 1056775 | J33: 968632
B34: Investment Properties | C34: 15908041 | D34: 16139908 | E34: 16139908 | F34: 18941077 | G34: 18922587 | H34: 42086561 | I34: 42658456 | J34: 42621346
B35: Investment in an associate | C35: 16108965 | D35: 17464229 | E35: 18924402 | F35: 19770106 | G35: 19447652 | H35: 22289013 | I35: 20664843 | J35: 21502182
B36: Total Non-Current Assets | C36: =SUM(C31:C35) -> 881900086 | D36: =SUM(D31:D35) -> 866635341 | E36: =SUM(E31:E35) -> 839682438 | F36: =SUM(F31:F35) -> 805887126 | G36: =SUM(G31:G35) -> 745458877 | H36: =SUM(H31:H35) -> 729695406 | I36: =SUM(I31:I35) -> 718021487 | J36: =SUM(J31:J35) -> 709930581
B38: Inventories | C38: 90948499 | D38: 88824637 | E38: 87997865 | F38: 58466609 | G38: 69565542 | H38: 109423030 | I38: 69450796 | J38: 66180974
B39: Trade Receivables | C39: 122338670 | D39: 205726134 | E39: 207719719 | F39: 140128631 | G39: 223224316 | H39: 343202685 | I39: 296070720 | J39: 263952251
B40: Prepayments & other current assets | C40: 19932683 | D40: 21495657 | E40: 42990606 | F40: 34371044 | G40: 51645200 | H40: 45040718 | I40: 41736989 | J40: 46471122
B41: Bank & Cash Balances | C41: 42653693 | D41: 10656986 | E41: 8491708 | F41: 8634070 | G41: 8916311 | H41: 9815988 | I41: 11888779 | J41: 4163400
B42: Total Current Assets | C42: =SUM(C38:C41) -> 275873545 | D42: =SUM(D38:D41) -> 326703414 | E42: =SUM(E38:E41) -> 347199898 | F42: =SUM(F38:F41) -> 241600354 | G42: =SUM(G38:G41) -> 353351369 | H42: =SUM(H38:H41) -> 507482421 | I42: =SUM(I38:I41) -> 419147284 | J42: =SUM(J38:J41) -> 380767747
B44: Total Assets | C44: =C42+C36 -> 1157773631 | D44: =D42+D36 -> 1193338755 | E44: =E42+E36 -> 1186882336 | F44: =F42+F36 -> 1047487480 | G44: =G42+G36 -> 1098810246 | H44: =H42+H36 -> 1237177827 | I44: =I42+I36 -> 1137168771 | J44: =J42+J36 -> 1090698328
B46: Equity
B47: Share Capital | C47: =348750000+26250000 -> 375000000 | D47: 375000000 | E47: 375000000 | F47: 375000000 | G47: 375000000 | H47: 450000000 | I47: 450000000 | J47: 450000000
B48: Statutory Reserve | C48: 13152955 | D48: 13152955 | E48: 13152955 | F48: 13152955 | G48: 18578520 | H48: 23344432 | I48: 23344432 | J48: 23344432
B49: General Reserve | C49: 10000000 | D49: 10000000 | E49: 10000000 | F49: 10000000 | G49: 10000000 | H49: 0 | I49: 0 | J49: 0
B50: Retained Earnings / (Accumulated Losses) | C50: -99344147 | D50: -22521080 | E50: -15758911 | F50: -50944900 | G50: 46598989 | H50: 161280906 | I50: 55612708 | J50: 26328642
B51: Total Equity | C51: =SUM(C47:C50) -> 298808808 | D51: =SUM(D47:D50) -> 375631875 | E51: =SUM(E47:E50) -> 382394044 | F51: =SUM(F47:F50) -> 347208055 | G51: =SUM(G47:G50) -> 450177509 | H51: =SUM(H47:H50) -> 634625338 | I51: =SUM(I47:I50) -> 528957140 | J51: =SUM(J47:J50) -> 499673074
B53: Term Loans | C53: 157945004 | D53: 198307871 | E53: 97615702 | F53: 183209407 | G53: 97884582 | H53: 67130498 | I53: 69267710 | J53: 55952059
B54: Employees defined benefits liabilities | C54: 34123925 | D54: 35544762 | E54: 35500501 | F54: 35882128 | G54: 39831613 | H54: 48107322 | I54: 48766362 | J54: 49975669
B55: Lease Liabilities | C55: 0 | D55: 0 | E55: 8512812 | F55: 8712179 | G55: 10854739 | H55: 7929201 | I55: 7206799 | J55: 11479954
B56: Non-current Liabilities | C56: =C53+C54+C55 -> 192068929 | D56: =D53+D54+D55 -> 233852633 | E56: =E53+E54+E55 -> 141629015 | F56: =F53+F54+F55 -> 227803714 | G56: =G53+G54+G55 -> 148570934 | H56: =H53+H54+H55 -> 123167021 | I56: =I53+I54+I55 -> 125240871 | J56: =J53+J54+J55 -> 117407682
B58: Trade Payables | C58: 111888591 | D58: 118922776 | E58: 133110309 | F58: 84954008 | G58: 125661359 | H58: 133950732 | I58: 119610739 | J58: 145228527
B59: Accruals & other current liabilities | C59: 37965678 | D59: 31665840 | E59: 35864723 | F59: 36229714 | G59: 47470359 | H59: 31015398 | I59: 33988154 | J59: 30889136
B60: Short Term Loans | C60: 338505763 | D60: 336032374 | E60: 369448865 | F60: 282427627 | G60: 234920846 | H60: 232512353 | I60: 267678203 | J60: 250163701
B61: Current portion of term loans | C61: 178098683 | D61: 94939225 | E61: 123142910 | F61: 67186753 | G61: 85678042 | H61: 70863227 | I61: 58946986 | J61: 40232391
B62: Current portion of lease liabilities | C62: 0 | D62: 0 | E62: 600639 | F62: 829708 | G62: 3189010 | H62: 3027121 | I62: 992455 | J62: 5544675
B63: Zakat payable / provision | C63: 437179 | D63: 2294032 | E63: 691831 | F63: 847901 | G63: 3142187 | H63: 8016637 | I63: 1754223 | J63: 1559142
B64: Current Liabilities | C64: =SUM(C58:C63) -> 666895894 | D64: =SUM(D58:D63) -> 583854247 | E64: =SUM(E58:E63) -> 662859277 | F64: =SUM(F58:F63) -> 472475711 | G64: =SUM(G58:G63) -> 500061803 | H64: =SUM(H58:H63) -> 479385468 | I64: =SUM(I58:I63) -> 482970760 | J64: =SUM(J58:J63) -> 473617572
B66: Total Shareholder's Equity & Liabilities | C66: =C64+C51+C56 -> 1157773631 | D66: =D64+D51+D56 -> 1193338755 | E66: =E64+E51+E56 -> 1186882336 | F66: =F64+F51+F56 -> 1047487480 | G66: =G64+G51+G56 -> 1098810246 | H66: =H64+H51+H56 -> 1237177827 | I66: =I64+I51+I56 -> 1137168771 | J66: =J64+J51+J56 -> 1090698328
B68: Check | C68: =C44-C66 -> 0 | D68: =D44-D66 -> 0 | E68: =E44-E66 -> 0 | F68: =F44-F66 -> 0 | G68: =G44-G66 -> 0 | H68: =H44-H66 -> 0 | I68: =I44-I66 -> 0 | J68: =J44-J66 -> 0

Sheet EBITDA
B1: Home Index (click here)
B3: - EBITDA representation:
J4: 6 months
B5: In millions SAR | C5: 2017 | D5: =C5+1 -> 2018 | E5: =D5+1 -> 2019 | F5: =E5+1 -> 2020 | G5: =F5+1 -> 2021 | H5: =G5+1 -> 2022 | I5: =H5+1 -> 2023 | J5: =$I$5+1 -> 2024
B6: Revenues | C6: 618298747 | D6: 764562777 | E6: 646481189 | F6: 563272730 | G6: 791000421 | H6: 982392366 | I6: 657861400 | J6: =+' - FS '!$J$8 -> 331615280
B7: (COGS) | C7: =-(591964630-75792442-2528572) -> -513643616 | D7: =-(598777348-72575327-524819-484633-21000) -> -525171569 | E7: =-(549474068-74321399) -> -475152669 | F7: =-(509029689-70729469) -> -438300220 | G7: =-(597406509-69515048-2715717) -> -525175744 | H7: =-(634195731-68179084) -> -566016647 | I7: =-543016453 -> -543016453 | J7: =+' - FS '!$J$9 +(32487182.95+3246710.87+92677.05) -> -2.6177519e+08
B8: Gross Profit | C8: =C6+C7 -> 104655131 | D8: =D6+D7 -> 239391208 | E8: =E6+E7 -> 171328520 | F8: =F6+F7 -> 124972510 | G8: =G6+G7 -> 265824677 | H8: =H6+H7 -> 416375719 | I8: =I6+I7 -> 114844947 | J8: =J6+J7 -> 69840094
B9: (General & Administrative Expenses) | C9: =-(29894040-1832467) -> -28061573 | D9: -30645365 | E9: =-(35892355-789561-442961) -> -34659833 | F9: =-(39295851-526840-276205) -> -38492806 | G9: =-(23452169-528029-500808-149602) -> -22273730 | H9: =-(60358913-4150606) -> -56208307 | I9: -74351200 | J9: =+' - FS '!$J$11+(743129.38+40437.23+1889.66) -> -30947366
B10: (Selling & Distributions Expenses) | C10: -25721758 | D10: -27417941 | E10: =-(27872343-12494) -> -27859849 | F10: =-(28406133-6594) -> -28399539 | G10: =-(48153561-2956) -> -48150605 | H10: =-(27443025-11491) -> -27431534 | I10: -43953499 | J10: =+' - FS '!$J$12 +(138+0+0) -> -16383900
B11: Operating Profit / Gross Profit (GP) | C11: =C8+C9+C10 -> 50871800 | D11: =D8+D9+D10 -> 181327902 | E11: =E8+E9+E10 -> 108808838 | F11: =F8+F9+F10 -> 58080165 | G11: =G8+G9+G10 -> 195400342 | H11: =H8+H9+H10 -> 332735878 | I11: =I8+I9+I10 -> -3459752 | J11: =J8+J9+J10 -> 22508828
B12: Share in results of an associate company | C12: 2156928 | D12: 2275264 | E12: 2840173 | F12: 3145704 | G12: 2956531 | H12: 2843014 | I12: 2978122 | J12: =+' - FS '!$J$14 -> 837337
B13: Reversal of expected credit losses | C13: -1200000 | D13: 0 | E13: 0 | F13: 0 | G13: 2344487 | H13: 0 | I13: 0 | J13: 0
B14: Other Income (net) | C14: 27344840 | D14: 1372852 | E14: 1623911 | F14: 869289 | G14: 1147654 | H14: 786773 | I14: -720365 | J14: =+' - FS '!$J$16 -> 630152
B15: Earning Before Int Tax Dep & Ammort -EBITDA | C15: =C11+C12+C13+C14 -> 79173568 | D15: =D11+D12+D13+D14 -> 184976018 | E15: =E11+E12+E13+E14 -> 113272922 | F15: =F11+F12+F13+F14 -> 62095158 | G15: =G11+G12+G13+G14 -> 201849014 | H15: =H11+H12+H13+H14 -> 336365665 | I15: =I11+I12+I13+I14 -> -1201995 | J15: =J11+J12+J13+J14 -> 23976317
B16: (Less) Depreciation & Ammortization | C16: =-(75792442+2528572+1832467) -> -80153481 | D16: =-(72575327+524819+484633+21000) -> -73605779 | E16: =-(74321399+789561+442961+12494) -> -75566415 | F16: =-(70729469+526840+276205+6594) -> -71539108 | G16: =-(69515048+2715717+528029+500808+149602+2956) -> -73412160 | H16: -72341181 | I16: -71999255 | J16: =-(32487182.95+3246710.87+92677.05+743129.38+40437.23+1889.66+138+0+0) -> -36612165
B17: EBIT | C17: =C15+C16 -> -979913 | D17: =D15+D16 -> 111370239 | E17: =E15+E16 -> 37706507 | F17: =F15+F16 -> -9443950 | G17: =G15+G16 -> 128436854 | H17: =H15+H16 -> 264024484 | I17: =I15+I16 -> -73201250 | J17: =J15+J16 -> -12635848
B18: (Less) Finance Cost (Interest) | C18: -33061003 | D18: -31560444 | E18: -34361598 | F18: -25380713 | G18: -20346696 | H18: -22607089 | I18: -34569636 | J18: =+' - FS '!$J$18 -> -16226629
B19: Earning Before Tax - EBT / PBT | C19: =C17+C18 -> -34040916 | D19: =D17+D18 -> 79809795 | E19: =E17+E18 -> 3344909 | F19: =F17+F18 -> -34824663 | G19: =G17+G18 -> 108090158 | H19: =H17+H18 -> 241417395 | I19: =I17+I18 -> -107770886 | J19: =J17+J18 -> -28862477
B20: (Zakat) | C20: -372338 | D20: -2294032 | E20: -653000 | F20: -801078 | G20: -2889609 | H20: -7973078 | I20: -356430 | J20: =+' - FS '!$J$19 -> -421589
B21: Net Income - (PAT) | C21: =C19+C20 -> -34413254 | D21: =D19+D20 -> 77515763 | E21: =E19+E20 -> 2691909 | F21: =F19+F20 -> -35625741 | G21: =G19+G20 -> 105200549 | H21: =H19+H20 -> 233444317 | I21: =I19+I20 -> -108127316 | J21: =J19+J20 -> -29284066
B22: Remeasurement of Employee Defined Benefits | C22: -289452 | D22: -692696 | E22: 4070260 | F22: 439752 | G22: -2172110 | H22: -3994835 | I22: 2461410 | J22: 0
B23: Share of OCI (loss) of an associate | C23: 0 | D23: 0 | E23: 0 | F23: 0 | G23: -58985 | H23: -1653 | I23: -2292 | J23: 0
B24: Other Comprehensive Profit (Loss) for the year | C24: =C22+C23 -> -289452 | D24: =D22+D23 -> -692696 | E24: =E22+E23 -> 4070260 | F24: =F22+F23 -> 439752 | G24: =G22+G23 -> -2231095 | H24: =H22+H23 -> -3996488 | I24: =I22+I23 -> 2459118 | J24: =J22+J23 -> 0
B25: Total Comprehensive Income for Year . | C25: =C21+C22+C23 -> -34702706 | D25: =D21+D22+D23 -> 76823067 | E25: =E21+E22+E23 -> 6762169 | F25: =F21+F22+F23 -> -35185989 | G25: =G21+G22+G23 -> 102969454 | H25: =H21+H22+H23 -> 229447829 | I25: =I21+I22+I23 -> -105668198 | J25: =J21+J22+J23 -> -29284066

Sheet FS with Schedules
B1: Home Index (click here) | F1: Seggregation of costs as per lead sheet / Audit FS
B2: INCOME STATEMENT | C2: IFRS Yr | J2: 6 months
B3: In millions SAR | C3: 2017 | D3: =C3+1 -> 2018 | E3: =D3+1 -> 2019 | F3: =E3+1 -> 2020 | G3: =F3+1 -> 2021 | H3: =G3+1 -> 2022 | I3: =H3+1 -> 2023 | J3: =I3+1 -> 2024
B4: Revenues | C4: 618298747 | D4: 764562777 | E4: 646481189 | F4: 563272730 | G4: 791000421 | H4: 982392366 | I4: 657861400 | J4: =+' - FS '!J8 -> 331615280
L5: Waraq | M5: ARC | N5: TOM | O5: Eimination | P5: Total
B6: Materials | C6: -409099826 | D6: -424278664 | E6: -399097008 | F6: -317207599 | G6: -386398583 | H6: -354561550 | I6: -3.2732671e+08 | J6: =-(194476274.38+58056479.43+761600.14-97099673) -> -1.5619468e+08 | L6: =175411510.19+19064764.19 -> 1.9447627e+08 | M6: 58056479 | N6: 684910.33 | O6: -97099673 | P6: =SUM(L6:O6) -> 1.5611799e+08
B7: Employees Cost | C7: 0 | D7: 0 | E7: 0 | F7: -45077162 | G7: -45644119 | H7: -93452426 | I7: -1.0640279e+08 | J7: =-(26238777.43+10967103.39+14601683.07) -> -51807564 | L7: 26238777 | M7: 10967103 | N7: 14601683 | P7: =SUM(L7:O7) -> 51807564
B8: Utilities & Spares Parts | C8: -68619609 | D8: -72420094 | E8: -69797021 | F8: -68649886 | G8: -75773189 | H8: -107032457 | I8: -91672766 | J8: =-48837039.72 -> -48837040 | L8: 44462882 | M8: 4374158.1 | N8: 0 | P8: =SUM(L8:O8) -> 48837040
B9: Depreciation on PPE (Direct Prodn PPE) | C9: -71624502 | D9: -72575327 | E9: -74321399 | F9: -70729469 | G9: =-69515048-2715717 -> -72230765 | H9: =-66790323-3647404 -> -70437727 | I9: =-(66872052+3888711) -> -70760763 | J9: -35826571 | L9: 32487183 | M9: 3246710.9 | N9: 92677.05 | P9: =SUM(L9:O9) -> 35826571
B10: Insurance | C10: -10250446 | D10: -9903922 | E10: -453809 | F10: -649940 | G10: -699962 | H10: -745515 | I10: 0 | J10: -432211 | L10: 280701.21 | M10: 151509.93 | N10: 47341.32 | P10: =SUM(L10:O10) -> 479552.46
B11: Inventory Impairment / Maintenance | C11: 0 | D11: 0 | E11: -1434604 | F11: -1840000 | G11: -458981 | H11: 0 | I11: 0 | P11: =SUM(L11:O11) -> 0
B12: Rent / Short term lease | C12: -7699268 | D12: -3136134 | E12: -265576 | F12: -83742 | G12: -85641 | H12: 0 | I12: 0 | J12: -260870.27 | M12: 260870.27 | P12: =SUM(L12:O12) -> 260870.27
B13: Consumables | C13: 0 | D13: 0 | E13: 0 | F13: 0 | G13: -10341034 | H13: 0 | I13: 0 | P13: =SUM(L13:O13) -> 0
B14: Others | C14: -24670981 | D14: -16463207 | E14: -4104651 | F14: -4791891 | G14: -5774235 | H14: -7966056 | I14: -17614190 | J14: -4242820.3 | L14: 1250423.6 | M14: 2992396.7 | N14: 29348.49 | P14: =SUM(L14:O14) -> 4272168.8
B15: (COGS) | C15: =SUM(C6:C14) -> -591964632 | D15: =SUM(D6:D14) -> -598777348 | E15: =SUM(E6:E14) -> -549474068 | F15: =SUM(F6:F14) -> -509029689 | G15: =SUM(G6:G14) -> -597406509 | H15: =SUM(H6:H14) -> -634195731 | I15: =SUM(I6:I14) -> -6.1377722e+08 | J15: =SUM(J6:J14) -> -2.9760176e+08 | L15: =SUM(L6:L14) -> 2.9919624e+08 | M15: =SUM(M6:M14) -> 80049229 | N15: =SUM(N6:N14) -> 15455960
L16: 297601757 | P16: =SUM(P6:P14) -> 2.9760176e+08
B17: Gross Profit | C17: =C4+C15 -> 26334115 | D17: =D4+D15 -> 165785429 | E17: =E4+E15 -> 97007121 | F17: =F4+F15 -> 54243041 | G17: =G4+G15 -> 193593912 | H17: =H4+H15 -> 348196635 | I17: =I4+I15 -> 44084184 | J17: =J4+J15 -> 34013523 | P17: =P16-L16 -> 0.12999994
B19: Employees related cost | C19: -23580455 | D19: -21875069 | E19: -21711452 | F19: -21106903 | G19: -23457728 | H19: -30198680 | I19: -33169213 | J19: -15953920
B20: Depreciation | C20: -925609 | D20: -524819 | E20: -789561 | F20: -526840 | G20: =-528029-500808 -> -1028837 | H20: =-405894-514813 -> -920707 | I20: =-949005-76105 -> -1025110 | J20: =-(520958+177354) -> -698312
B21: Ammortization | C21: -909126 | D21: -484633 | E21: -442961 | F21: -276205 | G21: -149602 | H21: -168614 | I21: -213104 | J21: -87144
B22: Rent | C22: -653658 | D22: -849916 | E22: -597276 | F22: -355593 | G22: -234516 | H22: 0 | I22: 0 | J22: -154294
B23: Insurance | C23: -87164 | D23: -205543 | E23: -8899245 | F23: -13778163 | G23: -19504947 | H23: -22302060 | I23: -22922780 | J23: -11080948
B24: Legal & Professional Fees | C24: -515715 | D24: -1929860 | E24: -1205740 | F24: -975848 | G24: -695162 | H24: -1086739 | I24: -5920526 | J24: -1291348
B25: Penalty | I25: -5450000
B26: Other Expenses | C26: -3222313 | D26: -4775525 | E26: -2246120 | F26: -2276299 | G26: -3082769 | H26: -5682113 | I26: -6888681 | J26: -2466858
B27: (General & Administrative Expenses) | C27: =SUM(C19:C26) -> -29894040 | D27: =SUM(D19:D26) -> -30645365 | E27: =SUM(E19:E26) -> -35892355 | F27: =SUM(F19:F26) -> -39295851 | G27: =SUM(G19:G26) -> -48153561 | H27: =SUM(H19:H26) -> -60358913 | I27: =SUM(I19:I26) -> -75589414 | J27: =SUM(J19:J26) -> -31732824
B29: Employees related cost | C29: -5609839 | D29: -5881479 | E29: -5427842 | F29: -4945081 | G29: -5192534 | H29: -6111520 | I29: -6364267 | J29: -2960215
B30: Freight | C30: -19071506 | D30: -18285066 | E30: -19539173 | F30: -20559118 | G30: -17059616 | H30: -19467577 | I30: -29373622 | J30: -12780335
B31: Depreciation | C31: -30721 | D31: -21000 | E31: -12494 | F31: -6594 | G31: -2956 | H31: -2039 | I31: -278 | J31: -138
B32: Allowance for Doubtful AR | C32: 0 | D32: -2491709 | E32: -1997470 | F32: -1500000 | G32: 0 | H32: 0 | I32: -6000000
B33: Others | C33: -1009692 | D33: -738687 | E33: -895364 | F33: -1395340 | G33: -1197063 | H33: -1861889 | I33: -2215610 | J33: -643350
B34: (Selling & Distributions Expenses) | C34: =SUM(C29:C33) -> -25721758 | D34: =SUM(D29:D33) -> -27417941 | E34: =SUM(E29:E33) -> -27872343 | F34: =SUM(F29:F33) -> -28406133 | G34: =SUM(G29:G33) -> -23452169 | H34: =SUM(H29:H33) -> -27443025 | I34: =SUM(I29:I33) -> -43953777 | J34: =SUM(J29:J33) -> -16384038
B36: Operating Profit | C36: =C17+C27+C34 -> -29281683 | D36: =D17+D27+D34 -> 107722123 | E36: =E17+E27+E34 -> 33242423 | F36: =F17+F27+F34 -> -13458943 | G36: =G17+G27+G34 -> 121988182 | H36: =H17+H27+H34 -> 260394697 | I36: =I17+I27+I34 -> -75459007 | J36: =J17+J27+J34 -> -14103339
B38: Share in results of an associate company | C38: 2156928 | D38: 2275264 | E38: 2840173 | F38: 3145704 | G38: 2956531 | H38: 2843014 | I38: 2978122 | J38: 837337
B40: Reversal of expected credit losses / Loss on lease termination | C40: -1200000 | D40: 0 | E40: 0 | F40: 0 | G40: 2344487 | H40: 0 | I40: -3100 | J40: 0
B41: (Loss) on disposal of Property & Equipment | C41: 0 | D41: 0 | E41: -180150 | F41: -897475 | G41: -1366450 | H41: -1191470 | I41: -1676228 | J41: -867725
B42: Gain on sale of PPE/ Rentals / Exchange Currency | C42: 133429 | D42: 70491 | E42: 0 | F42: 108749 | G42: =5000-91382 -> -86382 | H42: 0 | I42: -979493 | J42: 0
B43: Depreciation reversal | C43: 26460224 | D43: 0 | E43: 0 | F43: 0 | G43: 25383 | H43: 0 | I43: 0 | J43: 0
B44: HRDF Support | C44: 0 | D44: 0 | E44: 1168017 | F44: 1079300 | G44: 1999672 | H44: 1048384 | I44: 1522366 | J44: 252478
B45: Scrap Sales | C45: 624021 | D45: 417030 | E45: 152000 | F45: 61600 | G45: 244260 | H45: 191370 | I45: 0 | J45: 563630
B46: Sundry Income / Service Income | C46: 127166 | D46: 885331 | E46: =132068+351976 -> 484044 | F46: =342234+16447+158434 -> 517115 | G46: 331171 | H46: 738489 | I46: =276855+130852+8383 -> 416090 | J46: =682049-280 -> 681769
B47: Other Income (net) | C47: =SUM(C38:C46) -> 28301768 | D47: =SUM(D38:D46) -> 3648116 | E47: =SUM(E38:E46) -> 4464084 | F47: =SUM(F38:F46) -> 4014993 | G47: =SUM(G38:G46) -> 6448672 | H47: =SUM(H38:H46) -> 3629787 | I47: =SUM(I40:I46) -> -720365 | J47: =SUM(J40:J46) -> 630152
B49: EBIT | C49: =C36+C47 -> -979915 | D49: =D36+D47 -> 111370239 | E49: =E36+E47 -> 37706507 | F49: =F36+F47 -> -9443950 | G49: =G36+G47 -> 128436854 | H49: =H36+H47 -> 264024484 | I49: =I36+I38+I47 -> -73201250 | J49: =J36+J38+J47 -> -12635850
B51: Financial Charges - Bank Loans | I51: -32046357 | J51: -15805587
B52: Financial Charges – LTL | J52: 0
B53: Financial Charges - Lease Assets | I53: -605872 | J53: -421042
B54: S I D F Fees | J54: 0
B55: Amortization - Pre Operating Expenses | I55: 0 | J55: 0
B56: Net Interest | I56: -1917407 | J56: 0
B57: (Finance Cost) | C57: -33061003 | D57: -31560444 | E57: -34361598 | F57: -25380713 | G57: -20346696 | H57: -22607089 | I57: =SUM(I51:I56) -> -34569636 | J57: =SUM(J51:J56) -> -16226629
B59: (Zakat) | C59: -372338 | D59: -2294032 | E59: -653000 | F59: -801078 | G59: -2889609 | H59: -7973078 | I59: -356430 | J59: -421589
B61: Net Income | C61: =C49+C57+C59 -> -34413256 | D61: =D49+D57+D59 -> 77515763 | E61: =E49+E57+E59 -> 2691909 | F61: =F49+F57+F59 -> -35625741 | G61: =G49+G57+G59 -> 105200549 | H61: =H49+H57+H59 -> 233444317 | I61: =I49+I57+I59 -> -1.0812732e+08 | J61: =J49+J57+J59 -> -29284068
B62: Remeasurement of Employee Defined Benefits | C62: -289452 | D62: -692696 | E62: 4070260 | F62: 439752 | G62: -2172110 | H62: -3994835 | I62: 0 | J62: 0
B63: Share of OCI (loss) of an associate | C63: 0 | D63: 0 | E63: 0 | F63: 0 | G63: -58985 | H63: -1653 | I63: 0 | J63: 0
B64: Other Comprehensive Profit (Loss) for the year | C64: =C62+C63 -> -289452 | D64: =D62+D63 -> -692696 | E64: =E62+E63 -> 4070260 | F64: =F62+F63 -> 439752 | G64: =G62+G63 -> -2231095 | H64: =H62+H63 -> -3996488 | I64: =I62+I63 -> 0 | J64: =J62+J63 -> 0
B65: Total Comprehensive Income for Year . | C65: =C61+C64 -> -34702708 | D65: =D61+D64 -> 76823067 | E65: =E61+E64 -> 6762169 | F65: =F61+F64 -> -35185989 | G65: =G61+G64 -> 102969454 | H65: =H61+H64 -> 229447829 | I65: =I61+I64 -> -1.0812732e+08 | J65: =J61+J64 -> -29284068
B66: Budgeted revenue | C66: 0 | D66: 0 | E66: 0 | F66: 0 | G66: 0 | H66: 0 | I66: 0 | J66: 0
B68: BALANCE SHEET | C68: IFRS Yr
B69: In millions SAR | C69: 2017 | D69: =C69+1 -> 2018 | E69: =D69+1 -> 2019 | F69: =E69+1 -> 2020 | G69: =F69+1 -> 2021 | H69: =G69+1 -> 2022 | I69: =H69+1 -> 2023 | J69: =I69+1 -> 2024
B70: Assets
B72: Land | C72: 31220726 | D72: 32575968 | E72: 41387407 | F72: 38678750 | G72: 38169207 | H72: 15037538 | I72: 15037538 | J72: =(10988039.89-9072364.87)+(1023057.98-510894.44)+14586811 -> 17014650
B73: Buildings & Leasehold Improvements | C73: 180399450 | D73: 169119217 | E73: 159878817 | F73: 147614692 | G73: 135790233 | H73: 126417261 | I73: 118237150 | J73: =(219677162.81-115695724.06)+(6933078.69-3502381.33) -> 1.0741214e+08
B74: Plant & Machinery | C74: 599641652 | D74: 602643643 | E74: 565828988 | F74: 548720430 | G74: 498222837 | H74: 467816938 | I74: 466352612 | J74: =(943253869.87-570475444.66)+(27202089.77-14617889.17)+(6331.5-4282) -> 3.8536468e+08
B75: Furniture, Fixtures & Office Equipment | C75: 7510920 | D75: 6739507 | E75: 4842245 | F75: 4091650 | G75: 4405397 | H75: 4582996 | I75: 4103489 | J75: =(10578918.95+9249371.25+11060629.7-8240108.31-6563498.26-8038720.43)+(1134662.81+712427.95+831417.36-876566-326722-544524)+(113931+20201.35-113927-10713) -> 8986781.4
B76: Vehicles | C76: 14656626 | D76: 12748645 | E76: 11673869 | F76: 12818254 | G76: 12353737 | H76: 19087000 | I76: 21472009 | J76: =(47362406.94-30746741.75)+(10520158.81-7906566)+(777944-208423) -> 19798779
B77: Capital Work in Progress (CIP) | C77: 15800776 | D77: 8999807 | E77: 10969200 | F77: 5026288 | G77: 2912309 | H77: 19252957 | I77: 18671903 | J77: =(10988995.31+8999492.72+36326711.4+7761046.34+12331405.22-4670172) -> 71737479
B78: Projects in Progress | J78: =10903950.2+7014449.54 -> 17918400
B79: PP&E | C79: =SUM(C72:C77) -> 849230150 | D79: =SUM(D72:D77) -> 832826787 | E79: =SUM(E72:E77) -> 794580526 | F79: =SUM(F72:F77) -> 756950064 | G79: =SUM(G72:G77) -> 691853720 | H79: =SUM(H72:H77) -> 652194690 | I79: =SUM(I72:I78) -> 643874701 | J79: =SUM(J72:J78) -> 6.282329e+08
B81: Right of Use Assets | C81: 0 | D81: 0 | E81: 9564766 | F81: 9793474 | G81: 14929593 | H81: 12001937 | I81: 9766712 | J81: 16415374
B83: Intangible Assets | C83: 652930 | D83: 204417 | E83: 472836 | F83: 432405 | G83: 305325 | H83: 1123205 | I83: 1056775 | J83: 968632
B85: Investment Properties | C85: 15908041 | D85: 16139908 | E85: 16139908 | F85: 18941077 | G85: 18922587 | H85: 42086561 | I85: 42658456 | J85: 42621346
B87: Lease Hold Improvements | C87: 0 | D87: 0 | E87: 0 | F87: 0 | G87: 0 | H87: 0 | I87: 0 | J87: 190148
B89: Investment in an associate | C89: 16108965 | D89: 17464229 | E89: 18924402 | F89: 19770106 | G89: 19447652 | H89: 22289013 | I89: 20664843 | J89: 21502182
B91: Total Non-Current Assets | C91: =SUM(C79:C89) -> 881900086 | D91: =SUM(D79:D89) -> 866635341 | E91: =SUM(E79:E89) -> 839682438 | F91: =SUM(F79:F89) -> 805887126 | G91: =SUM(G79:G89) -> 745458877 | H91: =SUM(H79:H89) -> 729695406 | I91: =SUM(I79:I89) -> 718021487 | J91: =SUM(J79:J89) -> 7.0993058e+08
B93: Raw Materials | C93: 26132425 | D93: 27153765 | E93: 10079318 | F93: 4510455 | G93: 23903094 | H93: 15689416 | I93: 9985029 | J93: 1913079
B94: Spares parts & supplies (Not for sale) | C94: 35247725 | D94: 22603865 | E94: 30033550 | F94: 24218676 | G94: 26293746 | H94: 31627713 | I94: 34537356 | J94: 37165190
B95: Finished Goods (FG) | C95: 4663895 | D95: 19122885 | E95: 23603517 | F95: 6018363 | G95: 0 | H95: 29406002 | I95: 4451086 | J95: 8337666
B96: Work in Progress (WIP) | C96: 4157374 | D96: 3029093 | E96: 261000 | F96: 138700 | G96: 82557 | H96: 0 | I96: 0 | J96: 0
B97: Consumables | C97: 7960943 | D97: 8632933 | E97: 7921462 | F97: 10107262 | G97: 9070927 | H97: 8775861 | I97: 9212216 | J97: 26744876
B98: Materials for Re-sale | C98: 0 | D98: 0 | E98: 0 | F98: 0 | G98: 1249099 | H98: 0 | I98: 0 | J98: 0
B99: Chemicals | C99: 14097893 | D99: 10440020 | E99: 19691546 | F99: 18905681 | G99: 13235326 | H99: 30103880 | I99: 18644946 | J99: 0
B100: Less: Allowance for inventory (Slow moving) | C100: -1311756 | D100: -2157924 | E100: -3592528 | F100: -5432528 | G100: -4269207 | H100: -6179842 | I100: -7379837 | J100: -7979837
B101: Inventories | C101: =SUM(C93:C100) -> 90948499 | D101: =SUM(D93:D100) -> 88824637 | E101: =SUM(E93:E100) -> 87997865 | F101: =SUM(F93:F100) -> 58466609 | G101: =SUM(G93:G100) -> 69565542 | H101: =SUM(H93:H100) -> 109423030 | I101: =SUM(I93:I100) -> 69450796 | J101: =SUM(J93:J100) -> 66180974
B103: Trade Receivables | C103: 108614648 | D103: 180676868 | E103: 194152638 | F103: 131089847 | G103: 205972307 | H103: 306180639 | I103: 274187021 | J103: 250708975
B104: Receivable from Related Parties (Gulf Cartons) | C104: 15658128 | D104: 29475081 | E104: 19909741 | F104: 16870026 | G104: 22738764 | H104: 43408801 | I104: 34270454 | J104: 25630031
B105: Less (Allowance for RDD) | C105: -1934106 | D105: -4425815 | E105: -6342660 | F105: -7831242 | G105: -5486755 | H105: -6386755 | I105: -12386755 | J105: -12386755
B106: Trade Receivables | C106: =SUM(C103:C105) -> 122338670 | D106: =SUM(D103:D105) -> 205726134 | E106: =SUM(E103:E105) -> 207719719 | F106: =SUM(F103:F105) -> 140128631 | G106: =SUM(G103:G105) -> 223224316 | H106: =SUM(H103:H105) -> 343202685 | I106: =SUM(I103:I105) -> 296070720 | J106: =SUM(J103:J105) -> 263952251
B108: Insurance Claim received / receivable | C108: 0 | D108: 0 | E108: 28982932 | F108: 12021922 | G108: 22056295 | H108: 12420574 | I108: 7690548 | J108: 7868444
B109: Pre-Paid Expenses | C109: 1763569 | D109: 13115647 | E109: 6708439 | F109: 12096274 | G109: 14280506 | H109: 18815535 | I109: 12673712 | J109: 11159558
B110: Advance to suppliers | C110: 12775197 | D110: 5631255 | E110: 4837562 | F110: 8348790 | G110: 12775270 | H110: 11359580 | I110: 13632228 | J110: 19653717
B111: Employee Receivables | C111: 4700501 | D111: 2030236 | E111: 1851267 | F111: 996672 | G111: 1606441 | H111: 2238923 | I111: 6655516 | J111: 6844575
B112: Other Receivables | C112: 693416 | D112: 718519 | E112: 610406 | F112: 907386 | G112: 926688 | H112: 206106 | I112: 1084985 | J112: =941803+3025 -> 944828
B113: Prepayments & other current assets | C113: =SUM(C109:C112) -> 19932683 | D113: =SUM(D109:D112) -> 21495657 | E113: =SUM(E108:E112) -> 42990606 | F113: =SUM(F108:F112) -> 34371044 | G113: =SUM(G108:G112) -> 51645200 | H113: =SUM(H108:H112) -> 45040718 | I113: =SUM(I108:I112) -> 41736989 | J113: =SUM(J108:J112) -> 46471122
B115: Cash in Hand | C115: 189399 | D115: 444355 | E115: 152998 | F115: 621516 | G115: 574838 | H115: 134654 | I115: 353032 | J115: 494763
B116: Short term deposit | C116: 0 | D116: 0 | E116: 0 | F116: 0 | G116: 0 | H116: 0 | I116: 5400000 | J116: 0
B117: Cash at Bank | C117: 42464294 | D117: 10212631 | E117: 8338710 | F117: 8012554 | G117: 8341473 | H117: 9681334 | I117: 6135747 | J117: 3668638
B118: Bank & Cash Balances | C118: =SUM(C115:C117) -> 42653693 | D118: =SUM(D115:D117) -> 10656986 | E118: =SUM(E115:E117) -> 8491708 | F118: =SUM(F115:F117) -> 8634070 | G118: =SUM(G115:G117) -> 8916311 | H118: =SUM(H115:H117) -> 9815988 | I118: =SUM(I115:I117) -> 11888779 | J118: =SUM(J115:J117) -> 4163401
B120: Total Current Assets | C120: =C101+C106+C113+C118 -> 275873545 | D120: =D101+D106+D113+D118 -> 326703414 | E120: =E101+E106+E113+E118 -> 347199898 | F120: =F101+F106+F113+F118 -> 241600354 | G120: =G101+G106+G113+G118 -> 353351369 | H120: =H101+H106+H113+H118 -> 507482421 | I120: =I101+I106+I113+I118 -> 419147284 | J120: =J101+J106+J113+J118 -> 380767748
B122: Total Assets | C122: =C120+C91 -> 1157773631 | D122: =D120+D91 -> 1193338755 | E122: =E120+E91 -> 1186882336 | F122: =F120+F91 -> 1047487480 | G122: =G120+G91 -> 1098810246 | H122: =H120+H91 -> 1237177827 | I122: =I120+I91 -> 1137168771 | J122: =J120+J91 -> 1.0906983e+09
B124: Equity
...

Sheet  - CFS
B1: Home Index (click here)
B2: Cash Flow Statement | C2: IFRS Yr | J2: 6 months
B3: In millions SAR | C3: 2017 | D3: =C3+1 -> 2018 | E3: =D3+1 -> 2019 | F3: =E3+1 -> 2020 | G3: =F3+1 -> 2021 | H3: =G3+1 -> 2022 | I3: =H3+1 -> 2023 | J3: =I3+1 -> 2024
B5: Profit Before Tax (Zakat) PBT | C5: =' - FS '!C17+' - FS '!C18 -> -34040916 | D5: =' - FS '!D17+' - FS '!D18 -> 79809795 | E5: =' - FS '!E17+' - FS '!E18 -> 3344909 | F5: =' - FS '!F17+' - FS '!F18 -> -34824663 | G5: =' - FS '!G17+' - FS '!G18 -> 108090158 | H5: =' - FS '!H17+' - FS '!H18 -> 241417395 | I5: =' - FS '!I17+' - FS '!I18 -> -107770886 | J5: =' - FS '!J17+' - FS '!J18 -> -28862477
B7: Operating Activities
B9: A) Non Cash Adjustment to reconcile Tax with Net Income (PBT)
B10: Allowance against Accounts Receivable | C10: 0 | D10: 2491709 | E10: 1997470 | F10: 1500000 | G10: 0 | H10: 0 | I10: 0 | J10: 0
B11: Allowance for Obsolete Inventory | C11: 1311756 | D11: 846168 | E11: 1434604 | F11: 1840000 | G11: 0 | H11: 0 | I11: 0 | J11: 0
B12: Gain / (Loss) against disposal of investment property | C12: -133429 | D12: -70491 | E12: 0 | F12: -108749 | G12: 0 | H12: 0 | I12: 0 | J12: 0
B13: Depreciation of PPE | C13: =72580832-26460224 -> 46120608 | D13: 73121146 | E13: 74308579 | F13: 70357811 | G13: 70018812 | H13: 67307175 | I13: 67821335 | J13: 33744816
B14: Depreciation of Investmet Properties | C14: 0 | D14: 0 | E14: 0 | F14: 11168 | G14: 528033 | H14: 405894 | I14: 76105 | J14: 37110
B15: Depreciation of Right of Use Asset (Hire Purchase) | C15: 0 | D15: 0 | E15: 814875 | F15: 893924 | G15: 2715717 | H15: 3647404 | I15: 3888711 | J15: 1779789
B16: Ammortization of Intangible Assets | C16: 909126 | D16: 484633 | E16: 442961 | F16: 276205 | G16: 149602 | H16: 168614 | I16: 213104 | J16: 88144
B17: Provision for employees deemed benefit | C17: 5203638 | D17: 5544732 | E17: 5821266 | F17: 4868295 | G17: 3912230 | H17: 4464864 | I17: 5675711 | J17: 3029696
B18: (loss) on de-recognition of lease / assets | C18: -2450322 | D18: 2200821 | E18: 0 | F18: 0 | G18: 91382 | H18: 0 | I18: 3100 | J18: 0
B19: Discount on lease | C19: 0 | D19: 0 | E19: 0 | F19: 0 | G19: -5000 | H19: 0 | I19: 0 | J19: 0
B20: (loss) on disposal of PPE | C20: 0 | D20: 0 | E20: 180150 | F20: 897475 | G20: 1366450 | H20: 1191470 | I20: 1676228 | J20: 1283225
B21: Finance Costs (interest) | C21: 33061003 | D21: 31560444 | E21: 34361598 | F21: 25380713 | G21: 20346696 | H21: 22607086 | I21: 34569636 | J21: 16226629
B22: Share in results of an subsidary | C22: -2156928 | D22: -2275264 | E22: -2840173 | F22: -3145704 | G22: -2956531 | H22: -2843014 | I22: -2978122 | J22: -837337
C23: =SUM(C5:C22) -> 47824536 | D23: =SUM(D5:D22) -> 193713693 | E23: =SUM(E5:E22) -> 119866239 | F23: =SUM(F5:F22) -> 67946475 | G23: =SUM(G5:G22) -> 204257549 | H23: =SUM(H5:H22) -> 338366888 | I23: =SUM(I5:I22) -> 3174922 | J23: =SUM(J5:J22) -> 26489595
B24: B) Working capital adjustments:
B25: Inventories | C25: 15924424 | D25: -18122306 | E25: 0 | F25: 0 | G25: -11098933 | H25: -39857488 | I25: 39972234 | J25: 3269822
B26: Trade Receivables | C26: 40547988 | D26: -86522147 | E26: -24697053 | F26: 77010650 | G26: -83095685 | H26: -119978369 | I26: 47131965 | J26: 32118469
B27: Pre-payments & other Current Assets | C27: 0 | D27: 0 | E27: -607832 | F27: 27691256 | G27: 2604437 | H27: 6604482 | I27: 3303729 | J27: -4734133
B28: Accounts Payabels | C28: 52189263 | D28: -90673 | E28: 20010052 | F28: -46790475 | G28: 31581969 | H28: 8289373 | I28: -9739993 | J28: 25617788
B29: Accruals & Other Current Liabilities | C29: 0 | D29: 0 | E29: 0 | F29: 0 | G29: 23586027 | H29: -16466436 | I29: 2972756 | J29: -3099018
C30: =SUM(C25:C29) -> 108661675 | D30: =SUM(D25:D29) -> -104735126 | E30: =SUM(E25:E29) -> -5294833 | F30: =SUM(F25:F29) -> 57911431 | G30: =SUM(G25:G29) -> -36422185 | H30: =SUM(H25:H29) -> -161408438 | I30: =SUM(I25:I29) -> 83640691 | J30: =SUM(J25:J29) -> 53172928
B32: Cash from operations | C32: =C23+C30 -> 156486211 | D32: =D23+D30 -> 88978567 | E32: =E23+E30 -> 114571406 | F32: =F23+F30 -> 125857906 | G32: =G23+G30 -> 167835364 | H32: =H23+H30 -> 176958450 | I32: =I23+I30 -> 86815613 | J32: =J23+J30 -> 79662523
B34: Employees deemed benefit liabilities paid | C34: -1842714 | D34: -4816591 | E34: -1795267 | F34: -4046916 | G34: -2446783 | H34: -970913 | I34: -4472668 | J34: -1820389
B35: Tax (zakat) paid | C35: -240159 | D35: -437179 | E35: -2377452 | F35: -645008 | G35: -595323 | H35: -3098629 | I35: -6618844 | J35: -616670
B36: Finance Costs paid | C36: -30334593 | D36: -30735424 | E36: -35254587 | F36: -25771939 | G36: -18511468 | H36: -20599063 | I36: -32652228 | J36: -15805588
B38: Net Cash from Operating Activities | C38: =C32+C34+C35+C36 -> 124068745 | D38: =D32+D34+D35+D36 -> 52989373 | E38: =E32+E34+E35+E36 -> 75144100 | F38: =F32+F34+F35+F36 -> 95394043 | G38: =G32+G34+G35+G36 -> 146281790 | H38: =H32+H34+H35+H36 -> 152289845 | I38: =SUM(I32:I36) -> 43071873 | J38: =SUM(J32:J36) -> 61419876
B40: Investing Activities
B41: Purchase of PPE | C41: -42930689 | D41: -39520642 | E41: -36507718 | F41: -39270781 | G41: -26962837 | H41: -52471654 | I41: -62144784 | J41: -19386239
B42: Proceeds from disposal of PPE | C42: 183249 | D42: 72529 | E42: 265250 | F42: 1142368 | G42: 285783 | H42: 62170 | I42: 967210 | J42: 0
B43: Purchase of intangible assets | C43: -401694 | D43: -36120 | E43: -711380 | F43: -235774 | G43: 0 | H43: -986494 | I43: -146674 | J43: 0
B44: Addition to Right of use assets | C44: 0 | D44: 0 | E44: 0 | F44: 0 | G44: -22522 | H44: -622114 | I44: -191275 | J44: 0
B45: Addition to investment properties | C45: 500000 | D45: -231867 | E45: 0 | F45: 1800000 | G45: 0 | H45: 0 | I45: -648000 | J45: 0
B47: Net cash used In Investing Activities | C47: =SUM(C41:C45) -> -42649134 | D47: =SUM(D41:D45) -> -39716100 | E47: =SUM(E41:E45) -> -36953848 | F47: =SUM(F41:F45) -> -36564187 | G47: =SUM(G41:G45) -> -26699576 | H47: =SUM(H41:H45) -> -54018092 | I47: =SUM(I41:I45) -> -62163523 | J47: =SUM(J41:J45) -> -19386239
B49: Financing Activities
B50: Net movement in Short Term Loan | C50: 17037158 | D50: -2473389 | E50: 33416491 | F50: -87021238 | G50: -47506781 | H50: -2408493 | I50: 35165850 | J50: -17514502
B51: Dividends paid | C51: 0 | D51: 0 | E51: 0 | F51: 0 | G51: 0 | H51: -44988525 | I51: 0 | J51: 0
B52: Net movement in Term Loans | C52: -98644168 | D52: -42796591 | E52: -72488484 | F52: 29637548 | G52: -67360969 | H52: -45678044 | I52: -9779029 | J52: -32030246
B53: Payment of lease liabilities | C53: 0 | D53: 0 | E53: -1283537 | F53: -1303804 | G53: -4432223 | H53: -4297014 | I53: -4222380 | J53: -214268
B54: Increase in share capital | C54: 26250000 | D54: 0 | E54: 0 | F54: 0 | G54: 0 | H54: 0 | I54: 0 | J54: 0
B56: Net cash used in Financing Activities | C56: =SUM(C50:C55) -> -55357010 | D56: =SUM(D50:D55) -> -45269980 | E56: =SUM(E50:E55) -> -40355530 | F56: =SUM(F50:F55) -> -58687494 | G56: =SUM(G50:G55) -> -119299973 | H56: =SUM(H50:H55) -> -97372076 | I56: =SUM(I50:I55) -> 21164441 | J56: =SUM(J50:J55) -> -49759016
B58: Increase / (Decrease) in Bank & Cash Balances | C58: =C38+C47+C56 -> 26062601 | D58: =D38+D47+D56 -> -31996707 | E58: =E38+E47+E56 -> -2165278 | F58: =F38+F47+F56 -> 142362 | G58: =G38+G47+G56 -> 282241 | H58: =H38+H47+H56 -> 899677 | I58: =I38+I47+I56 -> 2072791 | J58: =J38+J47+J56 -> -7725379
B60: Bank & Cash Balances at Start of Year | C60: 16591092 | D60: =+' - FS '!C41 -> 42653693 | E60: =+' - FS '!D41 -> 10656986 | F60: =+' - FS '!E41 -> 8491708 | G60: =+' - FS '!F41 -> 8634070 | H60: =+' - FS '!G41 -> 8916311 | I60: =+' - FS '!H41 -> 9815988 | J60: =+' - FS '!I41 -> 11888779
B62: Bank & Cash Balances at End of Year | C62: =+' - FS '!C41 -> 42653693 | D62: =+' - FS '!D41 -> 10656986 | E62: =+' - FS '!E41 -> 8491708 | F62: =+' - FS '!F41 -> 8634070 | G62: =+' - FS '!G41 -> 8916311 | H62: =+' - FS '!H41 -> 9815988 | I62: =+' - FS '!I41 -> 11888779 | J62: =+' - FS '!J41 -> 4163400
B64: Check | C64: =C58-(C62-C60) -> 0 | D64: =D58-(D62-D60) -> 0 | E64: =E58-(E62-E60) -> 0 | F64: =F58-(F62-F60) -> 0 | G64: =G58-(G62-G60) -> 0 | H64: =H58-(H62-H60) -> 0 | I64: =I58-(I62-I60) -> 0 | J64: =J58-(J62-J60) -> 0

Sheet Imp Note
B1: Home Index (click here)
B3: CFS Vs FCFF Vs FCFE
B5: Cash Flow Statement (CFS)
B6: CFS is the net amount of cash and cash equivalents being transferred into and out of a
B7: company. Positive cash flow indicates that a company's liquid assets are increasing, enabling it to
B8: settle debts, reinvest in its business, return money to shareholders.
B10: Free Cash Flow to Firm (FCFF)
B11: FCFF is the cash flows a company produces through its operations after subtracting any outlays
B12: of cash for investment in fixed assets like property, plant, and equipment, and after depreciation
B13: expenses, cash flow taxes, working capital, and interest are accounted for. In other words, free
B14: cash flow to the firm is the cash left over after a company has paid its operating expenses and
B15: capital expenditures to enable to pay debt & equity holders both.
... B72: 95+30-50 = 75m
B74: FCFE | E74: Sample Data | H74: FCFF
E75: EBITDA = 200m
B76: Net Profit | E76: Depreciation = 20m | H76: EBIT x (1-tax)
A77: + | B77: Depreciation / Amortization | E77: EBIT = 180m | G77: + | H77: Depreciation / Amortization
A78: - | B78: Change in NWC | E78: Interest = 40m | G78: - | H78: Changes in NWC
A79: - | B79: Capital Expenditure | E79: EBT = 140m | G79: - | H79: Capital Expenditure
A80: + | B80: Change in Debt | E80: Tax at 25% = 140
E81: NP = 105
E83: Change in NWC = 30m
E84: Change in Debt = 50m
E85: Capex = 50m
B87: FCFE | C87: + | D87: Interest x (1-t) | F87: - | G87: Changes in Debt | I87: = | J87: .= FCFF

Sheet FCFF (Unlevered)
B1: Home Index (click here) | G1: Always FCFF > FCFE | J1: 6 months
B2: Year End | C2: 2017 | D2: =C2+1 -> 2018 | E2: =D2+1 -> 2019 | F2: =E2+1 -> 2020 | G2: =F2+1 -> 2021 | H2: =G2+1 -> 2022 | I2: =H2+1 -> 2023 | J2: =I2+1 -> 2024
B3: Free Cash Flows to the Firm (FCFF) (in millions) | C3: =+C52 -> -103.46138 | D3: =+D52 -> 46.433663 | E3: =+E52 -> 76.659813 | F3: =+F52 -> -26.289267 | G3: =+G52 -> 137.87349 | H3: =+H52 -> 116.23414 | I3: =+I52 -> -140.76998 | J3: =+J52 -> -45.748621
B4: Free Cash Flows to Equity (FCFE) (in millions) | C4: =+'FCFE (Levered)'!C50 -> -159.21562 | D4: =+'FCFE (Levered)'!D50 -> 1.698455 | E4: =+'FCFE (Levered)'!E50 -> 36.609028 | F4: =+'FCFE (Levered)'!F50 -> -86.017715 | G4: =+'FCFE (Levered)'!G50 -> 18.946206 | H4: =+'FCFE (Levered)'!H50 -> 62.583729 | I4: =+'FCFE (Levered)'!I50 -> -121.82128 | J4: =+'FCFE (Levered)'!J50 -> -96.250177
B6: Unlevered Free Cash Flow to Firm (FCFF)
B7: Cash Flow Available to both Debt & Equity Holders
B9: FCFF = EBIT * (1- Tax Rate) + Non Cash Charges - Capex - WCInv
B11: Zakat (Tax) | C11: =0.0254 -> 0.0254
J12: 6 months
B13: Year End | C13: 2017 | D13: =C13+1 -> 2018 | E13: =D13+1 -> 2019 | F13: =E13+1 -> 2020 | G13: =F13+1 -> 2021 | H13: =G13+1 -> 2022 | I13: =H13+1 -> 2023 | J13: =I13+1 -> 2024
B15: A) Earnings Before Interest & Tax (EBIT) | C15: =+EBITDA!C17 *(1-$C$11) -> -955023.21 | D15: =+EBITDA!D17 *(1-$C$11) -> 1.0854143e+08 | E15: =+EBITDA!E17 *(1-$C$11) -> 36748762 | F15: =+EBITDA!F17 *(1-$C$11) -> -9204073.7 | G15: =+EBITDA!G17 *(1-$C$11) -> 1.2517456e+08 | H15: =+EBITDA!H17 *(1-$C$11) -> 2.5731826e+08 | I15: =+EBITDA!I17 *(1-$C$11) -> -71341938 | J15: =+EBITDA!J17 *(1-$C$11) -> -12314897
B16: (EBIT = Operating Income)
B18: B) Non Cash Charges - CFS (Operating Activity)
B19: Allowance against Accounts Receivable | C19: 0 | D19: 2491709 | E19: 1997470 | F19: 1500000 | G19: 0 | H19: 0 | I19: 0 | J19: 0
B20: Allowance for Obsolete Inventory | C20: 1311756 | D20: 846168 | E20: 1434604 | F20: 1840000 | G20: 0 | H20: 0 | I20: 0 | J20: 0
B21: Gain / (Loss) against disposal of investment property | C21: -133429 | D21: -70491 | E21: 0 | F21: -108749 | G21: 0 | H21: 0 | I21: 0 | J21: 0
B22: Depreciation of PPE | C22: =72580832-26460224 -> 46120608 | D22: 73121146 | E22: 74308579 | F22: 70357811 | G22: 70018812 | H22: 67307175 | I22: 67821335 | J22: =+' - CFS'!J13 -> 33744816
B23: Depreciation of Investmet Properties | C23: 0 | D23: 0 | E23: 0 | F23: 11168 | G23: 528033 | H23: 405894 | I23: 76105 | J23: =+' - CFS'!J14 -> 37110
B24: Depreciation of Right of Use Asset (Hire Purchase) | C24: 0 | D24: 0 | E24: 814875 | F24: 893924 | G24: 2715717 | H24: 3647404 | I24: 3888711 | J24: =+' - CFS'!J15 -> 1779789
B25: Ammortization of Intangible Assets | C25: 909126 | D25: 484633 | E25: 442961 | F25: 276205 | G25: 149602 | H25: 168614 | I25: 213104 | J25: =+' - CFS'!J16 -> 88144
B26: Provision for employees deemed benefit | C26: 5203638 | D26: 5544732 | E26: 5821266 | F26: 4868295 | G26: 3912230 | H26: 4464864 | I26: 5675711 | J26: =+' - CFS'!J17 -> 3029696
B27: (loss) on de-recognition of lease / assets | C27: -2450322 | D27: 2200821 | E27: 0 | F27: 0 | G27: 91382 | H27: 0 | I27: 3100 | J27: 0
B28: Discount on lease | C28: 0 | D28: 0 | E28: 0 | F28: 0 | G28: -5000 | H28: 0 | I28: 0 | J28: 0
B29: (loss) on disposal of PPE | C29: 0 | D29: 0 | E29: 180150 | F29: 897475 | G29: 1366450 | H29: 1191470 | I29: 1676228 | J29: =+' - CFS'!J20 -> 1283225
B30: Finance Costs (interest) (To exclude any debt chrg) | C30: 0 | D30: 0 | E30: 0 | F30: 0 | G30: 0 | H30: 0 | I30: 0 | J30: 0
B31: Share in results of an subsidary | C31: -2156928 | D31: -2275264 | E31: -2840173 | F31: -3145704 | G31: -2956531 | H31: -2843014 | I31: -2978122 | J31: =+' - CFS'!J22 -> -837337
B32: B) Total Non-Cash Charges (NCC) | C32: =SUM(C19:C31) -> 48804449 | D32: =SUM(D19:D31) -> 82343454 | E32: =SUM(E19:E31) -> 82159732 | F32: =SUM(F19:F31) -> 77390425 | G32: =SUM(G19:G31) -> 75820695 | H32: =SUM(H19:H31) -> 74342407 | I32: =SUM(I19:I31) -> 76376172 | J32: =SUM(J19:J31) -> 39125443
B34: C) Capital Expenditure (Capex) - CFS
B35: Purchase of PPE | C35: -42930689 | D35: -39520642 | E35: -36507718 | F35: -39270781 | G35: -26962837 | H35: -52471654 | I35: -62144784 | J35: =+' - CFS'!J41 -> -19386239
B36: Proceeds from disposal of PPE | C36: 183249 | D36: 72529 | E36: 265250 | F36: 1142368 | G36: 285783 | H36: 62170 | I36: 967210 | J36: 0
B37: Purchase of intangible assets | C37: -401694 | D37: -36120 | E37: -711380 | F37: -235774 | G37: 0 | H37: -986494 | I37: -146674 | J37: 0
B38: Addition to Right of use assets | C38: 0 | D38: 0 | E38: 0 | F38: 0 | G38: -22522 | H38: -622114 | I38: -191275 | J38: 0
B39: Proceeds from disposal of investment properties | C39: 500000 | D39: -231867 | E39: 0 | F39: 1800000 | G39: 0 | H39: 0 | I39: -648000 | J39: 0
B40: C) Total Capex + Gains / (Loss) | C40: =SUM(C35:C39) -> -42649134 | D40: =SUM(D35:D39) -> -39716100 | E40: =SUM(E35:E39) -> -36953848 | F40: =SUM(F35:F39) -> -36564187 | G40: =SUM(G35:G39) -> -26699576 | H40: =SUM(H35:H39) -> -54018092 | I40: =SUM(I35:I39) -> -62163523 | J40: =SUM(J35:J39) -> -19386239
B42: D) Working Capital (WC) - CFS
B43: Inventories | C43: 15924424 | D43: -18122306 | E43: 0 | F43: 0 | G43: -11098933 | H43: -39857488 | I43: 39972234 | J43: =+' - CFS'!J25 -> 3269822
B44: Trade Receivables | C44: 40547988 | D44: -86522147 | E44: -24697053 | F44: 77010650 | G44: -83095685 | H44: -119978369 | I44: 47131965 | J44: =+' - CFS'!J26 -> 32118469
B45: Pre-payments & other Current Assets | C45: 0 | D45: 0 | E45: -607832 | F45: 27691256 | G45: 2604437 | H45: 6604482 | I45: 3303729 | J45: =+' - CFS'!J27 -> -4734133
B46: Accounts Payabels | C46: 52189263 | D46: -90673 | E46: 20010052 | F46: -46790475 | G46: 31581969 | H46: 8289373 | I46: -9739993 | J46: =+' - CFS'!J28 -> 25617788
B47: Accruals & Other Current Liabilities | C47: 0 | D47: 0 | E47: 0 | F47: 0 | G47: 23586027 | H47: -16466436 | I47: 2972756 | J47: =+' - CFS'!J29 -> -3099018
B48: D) Total Working Capital | C48: =SUM(C43:C47) -> 108661675 | D48: =SUM(D43:D47) -> -104735126 | E48: =SUM(E43:E47) -> -5294833 | F48: =SUM(F43:F47) -> 57911431 | G48: =SUM(G43:G47) -> -36422185 | H48: =SUM(H43:H47) -> -161408438 | I48: =SUM(I43:I47) -> 83640691 | J48: =SUM(J43:J47) -> 53172928
B50: Free Cash Flows to Firm (FCFF) | C50: =C15+C32+C40-C48 -> -1.0346138e+08 | D50: =D15+D32+D40+D48 -> 46433663 | E50: =E15+E32+E40+E48 -> 76659813 | F50: =F15+F32+F40-F48 -> -26289267 | G50: =G15+G32+G40+G48 -> 1.3787349e+08 | H50: =H15+H32+H40+H48 -> 1.1623414e+08 | I50: =I15+I32+I40-I48 -> -1.4076998e+08 | J50: =J15+J32+J40-J48 -> -45748621
B52: Free Cash Flows to Firm (FCFF) (in millions) | C52: =C50/1000000 -> -103.46138 | D52: =D50/1000000 -> 46.433663 | E52: =E50/1000000 -> 76.659813 | F52: =F50/1000000 -> -26.289267 | G52: =G50/1000000 -> 137.87349 | H52: =H50/1000000 -> 116.23414 | I52: =I50/1000000 -> -140.76998 | J52: =J50/1000000 -> -45.748621
B56: Make Waterfall Chart for both FCFF & FCFE (NY Stern)

Sheet FCFE (Levered)
B1: Home Index (click here)
B3: Levered Free Cash Flow to Equity (FCFE)
B4: Cash Flow Available to only Equity Holders (Common & Preference Stock As Dividends)
B6: FCFE = Net Income + Non Cash Charges - Capex - WCInv + Net Borrowings
J7: 6 months
B8: Year End | C8: 2017 | D8: =C8+1 -> 2018 | E8: =D8+1 -> 2019 | F8: =E8+1 -> 2020 | G8: =F8+1 -> 2021 | H8: =G8+1 -> 2022 | I8: =H8+1 -> 2023 | J8: =I8+1 -> 2024
B10: A) Net Income - Profit n (loss) | C10: =+' - FS '!C20 -> -34413254 | D10: =+' - FS '!D20 -> 77515763 | E10: =+' - FS '!E20 -> 2691909 | F10: =+' - FS '!F20 -> -35625741 | G10: =+' - FS '!G20 -> 105200549 | H10: =+' - FS '!H20 -> 233444317 | I10: =+' - FS '!I20 -> -108127316 | J10: =+' - FS '!J20 -> -29284066
B12: B) Non Cash Charges - CFS (Operating Activity)
B13: Allowance against Accounts Receivable | C13: 0 | D13: 2491709 | E13: 1997470 | F13: 1500000 | G13: 0 | H13: 0 | I13: 0 | J13: 0
B14: Allowance for Obsolete Inventory | C14: 1311756 | D14: 846168 | E14: 1434604 | F14: 1840000 | G14: 0 | H14: 0 | I14: 0 | J14: 0
B15: Gain / (Loss) against disposal of investment property | C15: -133429 | D15: -70491 | E15: 0 | F15: -108749 | G15: 0 | H15: 0 | I15: 0 | J15: 0
B16: Depreciation of PPE | C16: =72580832-26460224 -> 46120608 | D16: 73121146 | E16: 74308579 | F16: 70357811 | G16: 70018812 | H16: 67307175 | I16: 67821335 | J16: =+' - CFS'!J13 -> 33744816
B17: Depreciation of Investmet Properties | C17: 0 | D17: 0 | E17: 0 | F17: 11168 | G17: 528033 | H17: 405894 | I17: 76105 | J17: =+' - CFS'!J14 -> 37110
B18: Depreciation of Right of Use Asset (Hire Purchase) | C18: 0 | D18: 0 | E18: 814875 | F18: 893924 | G18: 2715717 | H18: 3647404 | I18: 3888711 | J18: =+' - CFS'!J15 -> 1779789
B19: Ammortization of Intangible Assets | C19: 909126 | D19: 484633 | E19: 442961 | F19: 276205 | G19: 149602 | H19: 168614 | I19: 213104 | J19: =+' - CFS'!J16 -> 88144
B20: Provision for employees deemed benefit | C20: 5203638 | D20: 5544732 | E20: 5821266 | F20: 4868295 | G20: 3912230 | H20: 4464864 | I20: 5675711 | J20: =+' - CFS'!J17 -> 3029696
B21: (loss) on de-recognition of lease / assets | C21: -2450322 | D21: 2200821 | E21: 0 | F21: 0 | G21: 91382 | H21: 0 | I21: 3100 | J21: =+' - CFS'!J18 -> 0
B22: Discount on lease | C22: 0 | D22: 0 | E22: 0 | F22: 0 | G22: -5000 | H22: 0 | I22: 0 | J22: =+' - CFS'!J19 -> 0
B23: (loss) on disposal of PPE | C23: 0 | D23: 0 | E23: 180150 | F23: 897475 | G23: 1366450 | H23: 1191470 | I23: 1676228 | J23: =+' - CFS'!J20 -> 1283225
B24: Finance Costs (interest) | C24: 33061003 | D24: 31560444 | E24: 34361598 | F24: 25380713 | G24: 20346696 | H24: 22607086 | I24: 34569636 | J24: =+' - CFS'!J21 -> 16226629
B25: Share in results of an subsidary | C25: -2156928 | D25: -2275264 | E25: -2840173 | F25: -3145704 | G25: -2956531 | H25: -2843014 | I25: -2978122 | J25: =+' - CFS'!J22 -> -837337
B26: B) Total Non-Cash Charges (NCC) | C26: =SUM(C13:C25) -> 81865452 | D26: =SUM(D13:D25) -> 113903898 | E26: =SUM(E13:E25) -> 116521330 | F26: =SUM(F13:F25) -> 102771138 | G26: =SUM(G13:G25) -> 96167391 | H26: =SUM(H13:H25) -> 96949493 | I26: =SUM(I13:I25) -> 110945808 | J26: =SUM(J13:J25) -> 55352072
B28: C) Capital Expenditure (Capex) - CFS
B29: Purchase of PPE | C29: -42930689 | D29: -39520642 | E29: -36507718 | F29: -39270781 | G29: -26962837 | H29: -52471654 | I29: -62144784 | J29: =+' - CFS'!J41 -> -19386239
B30: Proceeds from disposal of PPE | C30: 183249 | D30: 72529 | E30: 265250 | F30: 1142368 | G30: 285783 | H30: 62170 | I30: 967210 | J30: 0
B31: Purchase of intangible assets | C31: -401694 | D31: -36120 | E31: -711380 | F31: -235774 | G31: 0 | H31: -986494 | I31: -146674 | J31: 0
B32: Addition to Right of use assets | C32: 0 | D32: 0 | E32: 0 | F32: 0 | G32: -22522 | H32: -622114 | I32: -191275 | J32: 0
B33: Proceeds from disposal of investment properties | C33: 500000 | D33: -231867 | E33: 0 | F33: 1800000 | G33: 0 | H33: 0 | I33: -648000 | J33: 0
B34: C) Total Capex + Gains / (Loss) | C34: =SUM(C29:C33) -> -42649134 | D34: =SUM(D29:D33) -> -39716100 | E34: =SUM(E29:E33) -> -36953848 | F34: =SUM(F29:F33) -> -36564187 | G34: =SUM(G29:G33) -> -26699576 | H34: =SUM(H29:H33) -> -54018092 | I34: =SUM(I29:I33) -> -62163523 | J34: =SUM(J29:J33) -> -19386239
B36: D) Working Capital (WC) - CFS
B37: Inventories | C37: 15924424 | D37: -18122306 | E37: 0 | F37: 0 | G37: -11098933 | H37: -39857488 | I37: 39972234 | J37: =+' - CFS'!J25 -> 3269822
B38: Trade Receivables | C38: 40547988 | D38: -86522147 | E38: -24697053 | F38: 77010650 | G38: -83095685 | H38: -119978369 | I38: 47131965 | J38: =+' - CFS'!J26 -> 32118469
B39: Pre-payments & other Current Assets | C39: 0 | D39: 0 | E39: -607832 | F39: 27691256 | G39: 2604437 | H39: 6604482 | I39: 3303729 | J39: =+' - CFS'!J27 -> -4734133
B40: Accounts Payabels | C40: 52189263 | D40: -90673 | E40: 20010052 | F40: -46790475 | G40: 31581969 | H40: 8289373 | I40: -9739993 | J40: =+' - CFS'!J28 -> 25617788
B41: Accruals & Other Current Liabilities | C41: 0 | D41: 0 | E41: 0 | F41: 0 | G41: 23586027 | H41: -16466436 | I41: 2972756 | J41: =+' - CFS'!J29 -> -3099018
B42: D) Total Working Capital | C42: =SUM(C37:C41) -> 108661675 | D42: =SUM(D37:D41) -> -104735126 | E42: =SUM(E37:E41) -> -5294833 | F42: =SUM(F37:F41) -> 57911431 | G42: =SUM(G37:G41) -> -36422185 | H42: =SUM(H37:H41) -> -161408438 | I42: =SUM(I37:I41) -> 83640691 | J42: =SUM(J37:J41) -> 53172928
B44: A + B - C - D | C44: =(C10+C26+C34-C42) -> -103858611 | D44: =(D10+D26+D34+D42) -> 46968435 | E44: =(E10+E26+E34+E42) -> 76964558 | F44: =(F10+F26+F34-F42) -> -27330221 | G44: =(G10+G26+G34+G42) -> 138246179 | H44: =(H10+H26+H34+H42) -> 114967280 | I44: =(I10+I26+I34-I42) -> -142985722 | J44: =(J10+J26+J34-J42) -> -46491161
B45: Add
B46: Net Borrowing - CFS | C46: =' - CFS'!C56-' - CFS'!C51 -> -55357010 | D46: =' - CFS'!D56-' - CFS'!D51 -> -45269980 | E46: =' - CFS'!E56-' - CFS'!E51 -> -40355530 | F46: =' - CFS'!F56-' - CFS'!F51 -> -58687494 | G46: =' - CFS'!G56-' - CFS'!G51 -> -119299973 | H46: =' - CFS'!H56-' - CFS'!H51 -> -52383551 | I46: =' - CFS'!I56-' - CFS'!I51 -> 21164441 | J46: =' - CFS'!J56-' - CFS'!J51 -> -49759016
B48: Free Cash Flows to Equity (FCFE) | C48: =C44+C46 -> -159215621 | D48: =D44+D46 -> 1698455 | E48: =E44+E46 -> 36609028 | F48: =F44+F46 -> -86017715 | G48: =G44+G46 -> 18946206 | H48: =H44+H46 -> 62583729 | I48: =I44+I46 -> -121821281 | J48: =J44+J46 -> -96250177
B50: Free Cash Flows to Equity (FCFE) (in millions) | C50: =C48/1000000 -> -159.21562 | D50: =D48/1000000 -> 1.698455 | E50: =E48/1000000 -> 36.609028 | F50: =F48/1000000 -> -86.017715 | G50: =G48/1000000 -> 18.946206 | H50: =H48/1000000 -> 62.583729 | I50: =I48/1000000 -> -121.82128 | J50: =J48/1000000 -> -96.250177

Sheet WACC
B1: Home Index (click here)
A3: A) | B3: Calculation of BETA of (Company Name) | C3: =+C13 -> 0.76369711 | E3: Notes:
E4: Beta
A5: 1) | B5: MEPCO BETA | C5: 0.41 | E5: Beta is Relationship Measurement of a investment (stock or company) with Overall Market
B6: Source: | E6: Systematic Risk - Macro Risk = Outside market conditions risk
B7: https://finance.yahoo.com/quote/1202.SR?p=1202.SR | E7: Un-systematic Risk - Micro Risk = Inside company risk
E8: Market Beta will always be 1
A9: 2) | B9: Un-Lever & Re-Lever of MEPCO BETA | E9: Beta = 1 Means investment will move at same % as the market moves.
E10: Beta > 1 Means investment will move at a higher % than the market. More volatile stocks. Good for stocks during Bull Run
B11: Unlevered M BETA = Beta levered / (1+ (debt/equity) x (1-T) ) | C11: =+C5/1+(0.23)*(1-0.025) -> 0.63425 | E11: Beta = 0 Means investment will be neutral and has no cor-relation with market movement
E12: Beta < 1 Means investment will move at a lower % than the market. Less volatile stocks
B13: Re levering W Beta = Unlevered Mepco Beta x ( 1 + (debt/equity) x (1-T) ) | C13: =C11*((1++' Ratios '!J18)*(1-0.025)) -> 0.76369711 | E13: Beta <0 or -1 Means investment is INVERSE proportional to market risk. In general if market go up the invetment go down & vice versa
E14: Note: We need to un-lever & then again re-lever Mepco Beta for making it compatible as Waraq Beta
E15: (This is required as Co does not have a stock trading history, so we use comparable company beta)
A16: B) | B16: Cost of Equity | C16: =C22+(C23*(C24-C22)) -> 5.746265
B17: CAPM (Capital Asset Pricing Model)
B18: Helps determine what % return one can expect on an equity investment
B20: Ra = Rf + B (Rm - Rf)
B21: Ra = Estimate Return on Asset (investment) ????
B22: Rf = Risk Free Return (Govt Bonds) % | C22: 4.7
B23: B = Beta , Can find out from various websites or can calculate | C23: =+C3 -> 0.76369711
B24: Rm = Estimate Market Risk or Expected Risk Premium (country) ERP Aswat Damodaran % | C24: 6.07
B26: Source:
B27: https://ssrn.com/abstract=4509578
B28: https://www.saudiexchange.sa/wps/portal/saudiexchange/ourmarkets/sukuk-market-watch
A31: C) | B31: Cost of Debt (Pre Tax) | C31: =(H41/(H32+H33))*((C33+C34)/2) -> 7.8715791 | E31: Notes: | H31: 30 June 2024 FS
E32: Total Capital | H32: =+' - FS '!J47 -> 450000000
B33: Waraq All Bank Average charges @ 8.5% | C33: 8.5 | E33: Retained Earnings | H33: =+' - FS '!J50 -> 26328642 | I33: I have not used RE in the Cost of debt calculations. As I believe that it should
B34: EXIM Average charges @ 5.4% | C34: 5.4 | E34: Term Loans | H34: =+' - FS '!J53 -> 55952059 | I34: be equal to both waraq & mepco. But as waraq can convert RE to equity
B35: Therefore, Avg debt service charges @ 6.95% | E35: Lease Liabilities | H35: =+' - FS '!J55 -> 11479954 | I35: capital, Mepco cannot do it as its listed. So this is another way of calculation.
E36: Trade Payables | H36: =+' - FS '!J58 -> 145228527
B37: Formula | E37: Accruals & other current liabilities | H37: =+' - FS '!J59 -> 30889136
B38: Total Debt x % Avg Cost of debt | E38: Short Term Loans | H38: =+' - FS '!J60 -> 250163701
B39: Total Equity | E39: Current portion of term loans | H39: =+' - FS '!J61 -> 40232391
E40: Current portion of lease liabilities | H40: =+' - FS '!J62 -> 5544675
B41: Note: To confirm with Anas on 25 Sep in details | E41: Total Debt as on 30 June 2024 | H41: =SUM(H34:H40) -> 539490443
A44: D) | B44: WACC for W | C44: =C31+C16 -> 13.617844 | E44: Notes:
B45: (Weighted Average Cost of Capital - Debt / Equity) | E45: Why we need to compute WACC?
E46: It is used in Co Valuations / Capital Budgeting / others
B47: # = Wd x Rd (1-tax) + Wp x Rp + We x Re | E47: What is the cost on the capital that we acquire for the company
E48: Example
B49: Long Form Formula | E49: If WACC = 15%, then for every Riyal 100 that Waraq take (debt/equity) to run the company it has to earn
B50: # Total Debt x Cost of Debt + Total Preferred Capital x Cost of Pref Capital + Total Equity x Cost of Equity | E50: atleast 100 + 15 = Riyal 115 minimum . It also means that for profits after tax we need to make more than 15% minimum
B51: Total Capital Total Capital Total Capital | E51: of the equity invested. OR
B52: (Current Debt %) | E52: Any project that we invest, we need to make sure that it gives us a return of more than WACC 15 %. & this can be
E53: achieved by capital budgeting techniques.
B54: (No Preference Capital at Waraq) | E54: It is used in capital budgeting technique as a opportunity cost also known as Discounted Cash Flow
B55: Debt = Before Tax as it is tax deductible | E55: In most cases, a lower WACC indicates a healthy business that’s able to attract investors at a lower cost. By contrast, a
B56: Equity = After Tax figures | E56: higher WACC usually coincides with businesses that are seen as riskier and need to compensate investors with higher
E57: returns.
B59: Capital Budgeting for ZLD | D59: Below to be Re-worked with above WACC
B61: NPV - Net Present Value
B63: IRR - Internal Rate of Return
B65: PI - Profitability Index
B67: PBP - Payback Period
B68: (PBP is considered NOT using the DCF)
B71: ZLD - Project Capital Budgeting - NPV, IRR, Payback period, WACC
B74: A) Calculation of NPV - Net Present Value AND IRR
B75: Using formula of POWER | K75: Without Formula of POWER
B76: 6.36m fin chrg on 56.56m for 10 years | F76: Int % (oppor cost) | G76: Convert No | H76: (1+k) | K76: K (Discount rate) | L76: K% | M76: 1+K | N76: Cash Inflow | O76: Cash outflow | P76: NPV
B77: Proj Year | F77: 11 | G77: =F77/100 -> 0.11 | H77: =1+G77 -> 1.11 | K77: 11 | L77: =K77/100 -> 0.11 | M77: =1+L77 -> 1.11 | N77: =O94 -> 1.6181843e+08 | O77: 1000 | P77: =N77-O77 -> 1.6181743e+08
B78: 10 years
F79: NPV = | G79: FV (cash inflow)
G80: (1+k) ^n
C81: Project Capex | D81: 56358227 | K81: Use Variable discount rate.
C82: Year (n) | D82: FV Cash Inflow | E82: (1+k)^n | F82: NPV | K82: Year (n) | L82: FV | O82: PV
C83: 1 | D83: 27477000 | E83: =POWER(H$77,1) -> 1.11 | F83: =D83/E83 -> 24754054 | K83: 1 | L83: 27477000 | M83: (1+K)^1 | N83: =$M$77 -> 1.11 | O83: =L83/N83 -> 24754054
C84: 2 | D84: =+D83 -> 27477000 | E84: =POWER(H$77,2) -> 1.2321 | F84: =D84/E84 -> 22300950 | K84: 2 | L84: 27477000 | M84: (1+K)^2 | N84: =$M$77*N83 -> 1.2321 | O84: =L84/N84 -> 22300950
C85: 3 | D85: =+D84 -> 27477000 | E85: =POWER(H$77,3) -> 1.367631 | F85: =D85/E85 -> 20090946 | K85: 3 | L85: 27477000 | M85: (1+K)^3 | N85: =$M$77*N84 -> 1.367631 | O85: =L85/N85 -> 20090946
C86: 4 | D86: =+D85 -> 27477000 | E86: =POWER(H$77,4) -> 1.5180704 | F86: =D86/E86 -> 18099951 | K86: 4 | L86: 27477000 | M86: (1+K)^4 | N86: =$M$77*N85 -> 1.5180704 | O86: =L86/N86 -> 18099951
C87: 5 | D87: =+D86 -> 27477000 | E87: =POWER(H$77,5) -> 1.6850582 | F87: =D87/E87 -> 16306262 | K87: 5 | L87: 27477000 | M87: (1+K)^5 | N87: =$M$77*N86 -> 1.6850582 | O87: =L87/N87 -> 16306262
C88: 6 | D88: =+D87 -> 27477000 | E88: =POWER(H$77,6) -> 1.8704146 | F88: =D88/E88 -> 14690326 | K88: 6 | L88: 27477000 | M88: (1+K)^6 | N88: =$M$77*N87 -> 1.8704146 | O88: =L88/N88 -> 14690326
C89: 7 | D89: =+D88 -> 27477000 | E89: =POWER(H$77,7) -> 2.0761602 | F89: =D89/E89 -> 13234528 | K89: 7 | L89: 27477000 | M89: (1+K)^7 | N89: =$M$77*N88 -> 2.0761602 | O89: =L89/N89 -> 13234528
C90: 8 | D90: =+D89 -> 27477000 | E90: =POWER(H$77,8) -> 2.3045378 | F90: =D90/E90 -> 11922998 | K90: 8 | L90: 27477000 | M90: (1+K)^8 | N90: =$M$77*N89 -> 2.3045378 | O90: =L90/N90 -> 11922998
C91: 9 | D91: =+D90 -> 27477000 | E91: =POWER(H$77,9) -> 2.5580369 | F91: =D91/E91 -> 10741440 | K91: 9 | L91: 27477000 | M91: (1+K)^9 | N91: =$M$77*N90 -> 2.5580369 | O91: =L91/N91 -> 10741440
C92: 10 | D92: =+D91 -> 27477000 | E92: =POWER(H$77,10) -> 2.839421 | F92: =D92/E92 -> 9676972.9 | K92: 10 | L92: 27477000 | M92: (1+K)^10 | N92: =$M$77*N91 -> 2.839421 | O92: =L92/N92 -> 9676972.9
F94: =SUM(F83:F92) -> 1.6181843e+08 | N94: Total | O94: =SUM(O83:O92) -> 1.6181843e+08
E96: NPV = | F96: Inflow - Outflow
E97: NPV = | F97: =F94-D81 -> 1.054602e+08
C99: Note - NPV
C100: * Sukuk 10 year yield rate @ 4.4% (but have not taken this) ?
C101: What is the opportunity cost assumed by Abubakar? You can vary the cells in yellow
C102: My concern is that the FV inflow cannot be same amount each year. Therefore, the NPV will change
C103: Calculations for FV inflows need to be checked
C104: Equation: Conversally proportional
C105: NPV will increase if discount rates decrease and vice versa
B108: B) | C108: Internal Rate of Return IRR | L108: Profitability Index - PI
C109: The discount rate (ie opportunity rate) at which the NPV becomes ZERO is the IRR of the project | L109: =F94/D81 -> 2.8712477
C110: Therefore, if we vary the yellow cell the rate wherein the NPV is Zero will be our IRR for the project | L110: Since PI > 1, Project is feasible.
C111: Unable to match the % wherein the NPV = Zero. Maybe formula error or Base Zero year not considered
B113: C) | C113: Payback Period (Discounted) | F113: 2 years 7 months 6 days
C114: Time taken for the project to generate money to pay itself ie period in no of years to recover the
C115: initial investment total
C117: Initial Invest | D117: =+$D$12 -> 0
C118: NPV 1 | D118: =+-($F$14) -> 0 | E118: 1st Year
C119: NPV 2 | D119: =+-($F$15) -> 0 | E119: 2nd Year
C120: NPV 3 | D120: =-(D117+D118+D119) -> 0 | E120: 3rd Year (7 month 6 days)
D122: 26257 | E122: =F85/D122 -> 765.16531
B124: D) | C124: WACC - Cost of Debt / Equity
C125: not have the historical or current FS of waraq.

Sheet  Ratios 
B1: Home Index (click here)
A2: FINANCIAL RATIOS
A3: Sr No | C3: 2017 | D3: =C3+1 -> 2018 | E3: =D3+1 -> 2019 | F3: =E3+1 -> 2020 | G3: =F3+1 -> 2021 | H3: =G3+1 -> 2022 | I3: 2023 | J3: 2024 (6m) | K3: Description
A4: 1) | B4: Gross Margin | C4: =IFERROR(' - FS '!C10/' - FS '!C8,"No data") -> 0.042591251 | D4: =IFERROR(' - FS '!D10/' - FS '!D8,"No data") -> 0.21683691 | E4: =IFERROR(' - FS '!E10/' - FS '!E8,"No data") -> 0.15005405 | F4: =IFERROR(' - FS '!F10/' - FS '!F8,"No data") -> 0.096299782 | G4: =IFERROR(' - FS '!G10/' - FS '!G8,"No data") -> 0.24474565 | H4: =IFERROR(' - FS '!H10/' - FS '!H8,"No data") -> 0.35443744 | I4: =IFERROR(' - FS '!I10/' - FS '!I8,"No data") -> 0.067011355 | J4: =IFERROR(' - FS '!J10/' - FS '!J8,"No data") -> 0.10256923 | K4: GP / Revenues
A5: 2) | B5: Operating Margin | C5: =IFERROR(' - FS '!C13/' - FS '!C8,"No data") -> -0.047358467 | D5: =IFERROR(' - FS '!D13/' - FS '!D8,"No data") -> 0.14089376 | E5: =IFERROR(' - FS '!E13/' - FS '!E8,"No data") -> 0.051420557 | F5: =IFERROR(' - FS '!F13/' - FS '!F8,"No data") -> -0.023894185 | G5: =IFERROR(' - FS '!G13/' - FS '!G8,"No data") -> 0.15422012 | H5: =IFERROR(' - FS '!H13/' - FS '!H8,"No data") -> 0.26506181 | I5: =IFERROR(' - FS '!I13/' - FS '!I8,"No data") -> -0.1147035 | J5: =IFERROR(' - FS '!J13/' - FS '!J8,"No data") -> -0.042529213 | K5: Operating Profit / Revenues
A6: 3) | B6: Net Income Margin | C6: =IFERROR(' - FS '!C20/' - FS '!C8,"No data") -> -0.055657971 | D6: =IFERROR(' - FS '!D20/' - FS '!D8,"No data") -> 0.10138574 | E6: =IFERROR(' - FS '!E20/' - FS '!E8,"No data") -> 0.0041639402 | F6: =IFERROR(' - FS '!F20/' - FS '!F8,"No data") -> -0.063247765 | G6: =IFERROR(' - FS '!G20/' - FS '!G8,"No data") -> 0.13299683 | H6: =IFERROR(' - FS '!H20/' - FS '!H8,"No data") -> 0.23762839 | I6: =IFERROR(' - FS '!I20/' - FS '!I8,"No data") -> -0.16436185 | J6: =IFERROR(' - FS '!J20/' - FS '!J8,"No data") -> -0.088307348 | K6: Net Income / Revenues
A7: 4) | B7: Interest Coverage (Times Interest Coverage) | C7: =IFERROR(-' - FS '!C17/' - FS '!C18,"No data") -> -0.029639542 | D7: =IFERROR(-' - FS '!D17/' - FS '!D18,"No data") -> 3.5287919 | E7: =IFERROR(-' - FS '!E17/' - FS '!E18,"No data") -> 1.0973444 | F7: =IFERROR(-' - FS '!F17/' - FS '!F18,"No data") -> -0.3720916 | G7: =IFERROR(-' - FS '!G17/' - FS '!G18,"No data") -> 6.3124182 | H7: =IFERROR(-' - FS '!H17/' - FS '!H18,"No data") -> 11.678836 | I7: =IFERROR(-' - FS '!I17/' - FS '!I18,"No data") -> -2.1175013 | J7: =IFERROR(-' - FS '!J17/' - FS '!J18,"No data") -> -0.7787106 | K7: EBIT / Interest
A8: 5) | B8: Inventory Days | C8: =IFERROR((' - FS '!C38/-' - FS '!C9)*365,"No data") -> 56.078016 | D8: =IFERROR((' - FS '!D38/-' - FS '!D9)*365,"No data") -> 54.145322 | E8: =IFERROR((' - FS '!E38/-' - FS '!E9)*365,"No data") -> 58.45448 | F8: =IFERROR((' - FS '!F38/-' - FS '!F9)*365,"No data") -> 41.923512 | G8: =IFERROR((' - FS '!G38/-' - FS '!G9)*365,"No data") -> 42.502756 | H8: =IFERROR((' - FS '!H38/-' - FS '!H9)*365,"No data") -> 62.976466 | I8: =IFERROR((' - FS '!I38/-' - FS '!I9)*365,"No data") -> 41.300882 | J8: =IFERROR((' - FS '!J38/-' - FS '!J9)*365,"No data") -> 81.169062 | K8: (Inventory / COGS)*365
A9: 6) | B9: Accounts Receivable Days | C9: =IFERROR((' - FS '!C39/' - FS '!C8)*365,"No data") -> 72.220128 | D9: =IFERROR((' - FS '!D39/' - FS '!D8)*365,"No data") -> 98.213046 | E9: =IFERROR((' - FS '!E39/' - FS '!E8)*365,"No data") -> 117.2775 | F9: =IFERROR((' - FS '!F39/' - FS '!F8)*365,"No data") -> 90.803172 | G9: =IFERROR((' - FS '!G39/' - FS '!G8)*365,"No data") -> 103.00484 | H9: =IFERROR((' - FS '!H39/' - FS '!H8)*365,"No data") -> 127.5142 | I9: =IFERROR((' - FS '!I39/' - FS '!I8)*365,"No data") -> 164.26836 | J9: =IFERROR((' - FS '!J39/' - FS '!J8)*365,"No data") -> 290.52513 | K9: (AR / Revenues)*365
A10: 7) | B10: Accounts Payable Days | C10: =IFERROR((' - FS '!C58/-' - FS '!C9)*365,"No data") -> 68.989486 | D10: =IFERROR((' - FS '!D58/-' - FS '!D9)*365,"No data") -> 72.49241 | E10: =IFERROR((' - FS '!E58/-' - FS '!E9)*365,"No data") -> 88.421394 | F10: =IFERROR((' - FS '!F58/-' - FS '!F9)*365,"No data") -> 60.916315 | G10: =IFERROR((' - FS '!G58/-' - FS '!G9)*365,"No data") -> 76.775856 | H10: =IFERROR((' - FS '!H58/-' - FS '!H9)*365,"No data") -> 77.092946 | I10: =IFERROR((' - FS '!I58/-' - FS '!I9)*365,"No data") -> 71.129913 | J10: =IFERROR((' - FS '!J58/-' - FS '!J9)*365,"No data") -> 178.11861 | K10: (AP / COGS)*365
A11: 8) | B11: Net Working Capital | C11: =IFERROR(' - FS '!C38+' - FS '!C39+' - FS '!C40-' - FS '!C64,"No data") -> -433676042 | D11: =IFERROR(' - FS '!D38+' - FS '!D39+' - FS '!D40-' - FS '!D64,"No data") -> -267807819 | E11: =IFERROR(' - FS '!E38+' - FS '!E39+' - FS '!E40-' - FS '!E64,"No data") -> -324151087 | F11: =IFERROR(' - FS '!F38+' - FS '!F39+' - FS '!F40-' - FS '!F64,"No data") -> -239509427 | G11: =IFERROR(' - FS '!G38+' - FS '!G39+' - FS '!G40-' - FS '!G64,"No data") -> -155626745 | H11: =IFERROR((' - FS '!H38+' - FS '!H39+' - FS '!H40-' - FS '!H64),"No data") -> 18280965 | I11: =IFERROR((' - FS '!I38+' - FS '!I39+' - FS '!I40-' - FS '!I64),"No data") -> -75712255 | J11: =IFERROR((' - FS '!J38+' - FS '!J39+' - FS '!J40-' - FS '!J64),"No data") -> -97013225 | K11: CA (except cash) - CL
A12: 9) | B12: Cash Conversion Cycle (CCC) | C12: =IFERROR(C8+C9-C10,"No data") -> 59.308658 | D12: =IFERROR(D8+D9-D10,"No data") -> 79.865958 | E12: =IFERROR(E8+E9-E10,"No data") -> 87.310586 | F12: =IFERROR(F8+F9-F10,"No data") -> 71.810368 | G12: =IFERROR(G8+G9-G10,"No data") -> 68.731744 | H12: =IFERROR(H8+H9-H10,"No data") -> 113.39772 | I12: =IFERROR(I8+I9-I10,"No data") -> 134.43933 | J12: =IFERROR(J8+J9-J10,"No data") -> 193.57558 | K12: (Inventory + AR) - AP
A13: 10) | B13: Current Ratio | C13: =IFERROR(' - FS '!C42/' - FS '!C64,"No data") -> 0.41366808 | D13: =IFERROR(' - FS '!D42/' - FS '!D64,"No data") -> 0.55956331 | E13: =IFERROR(' - FS '!E42/' - FS '!E64,"No data") -> 0.52379126 | F13: =IFERROR(' - FS '!F42/' - FS '!F64,"No data") -> 0.51134979 | G13: =IFERROR(' - FS '!G42/' - FS '!G64,"No data") -> 0.7066154 | H13: =IFERROR(' - FS '!H42/' - FS '!H64,"No data") -> 1.0586104 | I13: =IFERROR(' - FS '!I42/' - FS '!I64,"No data") -> 0.8678523 | J13: =IFERROR(' - FS '!J42/' - FS '!J64,"No data") -> 0.80395612 | K13: CA / CL
A14: 11) | B14: Quick Ratio | C14: =IFERROR((' - FS '!C42-' - FS '!C38)/' - FS '!C64,"No data") -> 0.27729222 | D14: =IFERROR((' - FS '!D42-' - FS '!D38)/' - FS '!D64,"No data") -> 0.40742836 | E14: =IFERROR((' - FS '!E42-' - FS '!E38)/' - FS '!E64,"No data") -> 0.39103629 | F14: =IFERROR((' - FS '!F42-' - FS '!F38)/' - FS '!F64,"No data") -> 0.38760457 | G14: =IFERROR((' - FS '!G42-' - FS '!G38)/' - FS '!G64,"No data") -> 0.56750151 | H14: =IFERROR((' - FS '!H42-' - FS '!H38)/' - FS '!H64,"No data") -> 0.83035348 | I14: =IFERROR((' - FS '!I42-' - FS '!I38)/' - FS '!I64,"No data") -> 0.72405312 | J14: =IFERROR((' - FS '!J42-' - FS '!J38)/' - FS '!J64,"No data") -> 0.66422108 | K14: (CA - Inventory) / CL
A15: 12) | B15: Asset Turnover (A T/o) | C15: =IFERROR(' - FS '!C8/' - FS '!C44,"No data") -> 0.53404114 | D15: =IFERROR(' - FS '!D8/' - FS '!D44,"No data") -> 0.64069215 | E15: =IFERROR(' - FS '!E8/' - FS '!E44,"No data") -> 0.54468853 | F15: =IFERROR(' - FS '!F8/' - FS '!F44,"No data") -> 0.53773696 | G15: =IFERROR(' - FS '!G8/' - FS '!G44,"No data") -> 0.7198699 | H15: =IFERROR(' - FS '!H8/' - FS '!H44,"No data") -> 0.79405914 | I15: =IFERROR(' - FS '!I8/' - FS '!I44,"No data") -> 0.57850815 | J15: =IFERROR(' - FS '!J8/' - FS '!J44,"No data") -> 0.30403941 | K15: Revenues / Total Assets
A16: 13) | B16: Return on Equity (ROE) | C16: =IFERROR(' - FS '!C20/' - FS '!C51,"No data") -> -0.11516814 | D16: =IFERROR(' - FS '!D20/' - FS '!D51,"No data") -> 0.20636098 | E16: =IFERROR(' - FS '!E20/' - FS '!E51,"No data") -> 0.0070396206 | F16: =IFERROR(' - FS '!F20/' - FS '!F51,"No data") -> -0.10260632 | G16: =IFERROR(' - FS '!G20/' - FS '!G51,"No data") -> 0.23368682 | H16: =IFERROR(' - FS '!H20/' - FS '!H51,"No data") -> 0.36784588 | I16: =IFERROR(' - FS '!I20/' - FS '!I51,"No data") -> -0.20441603 | J16: =IFERROR(' - FS '!J20/' - FS '!J51,"No data") -> -0.058606452 | K16: Net Income (PAT) / Shareholders Total
A17: 14) | B17: Return on Assets (ROA) | C17: =IFERROR(' - FS '!C20/' - FS '!C44,"No data") -> -0.029723646 | D17: =IFERROR(' - FS '!D20/' - FS '!D44,"No data") -> 0.064957048 | E17: =IFERROR(' - FS '!E20/' - FS '!E44,"No data") -> 0.0022680504 | F17: =IFERROR(' - FS '!F20/' - FS '!F44,"No data") -> -0.03401066 | G17: =IFERROR(' - FS '!G20/' - FS '!G44,"No data") -> 0.095740415 | H17: =IFERROR(' - FS '!H20/' - FS '!H44,"No data") -> 0.188691 | I17: =IFERROR(' - FS '!I20/' - FS '!I44,"No data") -> -0.095084669 | J17: =IFERROR(' - FS '!J20/' - FS '!J44,"No data") -> -0.026848914 | K17: Net Income (PAT) / Total Assets
A18: 15) | B18: Debt-to-equity (DE) | C18: =IFERROR(' - FS '!C56/' - FS '!C51,"No data") -> 0.64278202 | D18: =IFERROR(' - FS '!D56/' - FS '!D51,"No data") -> 0.62255801 | E18: =IFERROR(' - FS '!E56/' - FS '!E51,"No data") -> 0.37037453 | F18: =IFERROR(' - FS '!F56/' - FS '!F51,"No data") -> 0.65610147 | G18: =IFERROR(' - FS '!G56/' - FS '!G51,"No data") -> 0.33002745 | H18: =IFERROR(' - FS '!H56/' - FS '!H51,"No data") -> 0.19407832 | I18: =IFERROR(' - FS '!I56/' - FS '!I51,"No data") -> 0.23676941 | J18: =IFERROR(' - FS '!J56/' - FS '!J51,"No data") -> 0.234969 | K18: Debt (Non CL) / Shareholders Total
A19: 16) | B19: Operating Cash Flow to Debt | C19: =' - CFS'!C38/(' - FS '!C56+' - FS '!C64) -> 0.14443984 | D19: =' - CFS'!D38/(' - FS '!D56+' - FS '!D64) -> 0.064802406 | E19: =' - CFS'!E38/(' - FS '!E56+' - FS '!E64) -> 0.093406083 | F19: =' - CFS'!F38/(' - FS '!F56+' - FS '!F64) -> 0.13622283 | G19: =' - CFS'!G38/(' - FS '!G56+' - FS '!G64) -> 0.22552329 | H19: =' - CFS'!H38/(' - FS '!H56+' - FS '!H64) -> 0.25274121 | I19: =' - CFS'!I38/(' - FS '!I56+' - FS '!I64) -> 0.070817247 | J19: =' - CFS'!J38/(' - FS '!J56+' - FS '!J64) -> 0.1039209 | K19: Operating Cash Flow / Total Debt
C21: ROE | D21: ROA | E21: Debt-to Equity | F21: Asset turnover
B22: Value | C22: =J16 -> -0.058606452 | D22: =J17 -> -0.026848914 | E22: =J18 -> 0.234969 | F22: =J15 -> 0.30403941
B23: Blank | C23: =C25-(-C22) -> 0.94139355 | D23: =D25-(-D22) -> 0.97315109 | E23: =E25-E22 -> 1.765031 | F23: =F25-F22 -> 0.69596059
B24: Bottom | C24: =C25/0.8-C25 -> 0.25 | D24: =D25/0.8-D25 -> 0.25 | E24: =E25/0.8-E25 -> 0.5 | F24: =F25/0.8-F25 -> 0.25
B25: Top | C25: 1 | D25: 1 | E25: 2 | F25: 1
B26: (Please ignore this above table as it is used for the dashboard Waterfall / Line charts.
B27: Need to define the Min / Max range as required to have a proper representation.)

Sheet Dashboard
B1: Home Index (click here)
B3: 2024 YEAR INCOME STATEMENT (In Thousands) | Y3: 2024 (6m) ASSET TURNOVER RATIO | AF3: 2024 (6m) RETURN ON EQUITY | AM3: 2024 (6m) RETURN ON ASSETS
B28: GROSS PROFIT MARGIN | N28: OPERATING PROFIT MARGIN | AF28: NET INCOME MARGIN
B42: CASH CONVERSION CYCLE | N42: DEBT-TO-EQUITY | AF42: CURRENT RATIO & QUICK RATIO
B56: Operating Cash Flow Vs Total Debt

Sheet Resource
B1: Home Index (click here) | H1: UnLevered means Debt Free
H2: Leverage means Interest & Debt
B3: Interest Coverage | C3: Net Working Capital (NWC) | D3: Cash Conversion Cycle (CCC) | E3: Asset Turnover Ratio (A T/o) | F3: Return on Assets Ratio (RoA) | G3: Debt to Equity Ratio (DE) | H3: FCFF - Free Cash Flow to Firm | I3: FCFE - Free Cash Flow to Equity
B4: On the other hand, an interest coverage ratio of 1.5 is generally considered a minimum acceptable ratio for a company and the tipping point below which lenders will likely refuse to lend the company more money, as the company’s risk for default may be perceived as too high. | C4: Working capital is important because it is necessary for businesses to remain solvent. In theory, a business could become bankrupt even if it is profitable. After all, a business cannot rely on paper profits to pay its bills—those bills need to be paid in cash readily in hand. Say a company has accumulated 1 million in cash due to its previous years’ retained earnings. If the company were to invest all 1 million at once, it could find itself with insufficient current assets to pay for its current liabilities. | D4: The cash conversion cycle (CCC) is a metric that expresses the time (measured in days) that it takes for a company to convert its investments in inventory and other resources into cash flows from sales. Also called the net operating cycle or simply cash cycle, CCC attempts to measure how long each net input dollar is tied up in the production and sales process before it gets converted into cash received. | E4: The asset turnover ratio measures the value of a company's sales or revenues relative to the value of its assets. The asset turnover ratio can be used as an indicator of the efficiency with which a company is using its assets to generate revenue. | F4: Return on assets is a profitability ratio that provides how much profit a company can generate from its assets. In other words, return on assets (ROA) measures how efficient a company's management is in earning a profit from their economic resources or assets on their balance sheet. | G4: It is a measure of the degree to which a company is financing its operations with debt rather than its own resources. Debt-to-equity ratio is a particular type of gearing ratio. | H4: FCFF - Unlevered Free Cash Flows. Cash Flow BEFORE Deduction of Interest & Debt payments. Cash Flows available for Debt & Equity Holders (Common/Preferred) . | I4: FCFE - Levered Free Cash Flows. Cash Flow AFTER Deduction of Interest & Debt payments. Cash Flows available for only Equity Holders (Common/Preferred) .
B5: If a company’s ratio is below one, it will likely need to spend some of its cash reserves to meet the difference or borrow more, which will be difficult for the reasons stated above. Otherwise, even if earnings are low for a single month, the company risks falling into bankruptcy. | C5: Working capital is also a measure of a company’s operational efficiency and short-term financial health. If a company has substantial positive NWC, then it could have the potential to invest in expansion and grow the company. If a company’s current assets do not exceed its current liabilities, then it may have trouble growing or paying back creditors. It might even go bankrupt. | D5: This metric takes into account how much time the company needs to sell its inventory, how much time it takes to collect receivables, and how much time it has to pay its bills. | E5: The higher the asset turnover ratio, the more efficient a company is at generating revenue from its assets. Conversely, if a company has a low asset turnover ratio, it indicates it is not efficiently using its assets to generate sales. | F5: ROA is shown as a percentage, and the higher the number, the more efficient a company's management is at managing its balance sheet to generate profits. | G5: D/E ratio measures how much debt a company has taken on relative to the value of its assets net of liabilities. Debt must be repaid or refinanced, imposes interest expense that typically can’t be deferred, and could impair or destroy the value of equity in the event of a default. | H5: The FCFF calculation is an indicator of a company's operations and its performance. FCFF considers all cash inflows in the form of revenues, all cash outflows in the form of ordinary expenses, and all reinvested cash to grow the business. The money left over after conducting all these operations represents a company's FCFF. | I5: This metric is to be used for determination on divident policy and for creditors / analysts to assess if company is window dressing of payment dividends through internal sources or debt financing.
B6: What Does a Bad Interest Coverage Ratio Indicate? | C6: What Does a Positive or Negative WC indicate? | D6: What does a Higher or Lower CCC indicate? | E6: What does a Higher or Lower A T/o indicate? | F6: What does a Higher or Lower RoA indicate? | G6: What does a Higher or Lower DE indicate? | H6: What does a Positive or Negative FCFF indicate? | I6: What does a Higher or Lower FCFE indicate?
B7: A bad interest coverage ratio is any number below one as this means that the company's current earnings are insufficient to service its outstanding debt. The chances of a company being able to continue to meet its interest expenses on an ongoing basis are still doubtful even with an interest coverage ratio below 1.5, especially if the company is vulnerable to seasonal or cyclical dips in revenues. | C7: When a working capital calculation is positive, this means the company's current assets are greater than its current liabilities. The company has more than enough resources to cover its short-term debt, and there is residual cash should all current assets be liquidated to pay this debt. | D7: Inventory management, sales realization, and payables are the three key ingredients of business. If any of these goes for a toss—say, inventory mismanagement, sales constraints, or payables increasing in number, value, or frequency—then the business is set to suffer. Beyond the monetary value involved, CCC accounts for the time involved in these processes that provides another view of the company’s operating efficiency. | E7: Generally, a higher ratio is favored because it implies that the company is efficient in generating sales or revenues from its asset base. A lower ratio indicates that a company is not using its assets efficiently and may have internal problems. | F7: Companies with a low ROA usually have more assets involved in generating their profits. Companies with a high ROA usually have fewer assets involved in generating their profits | G7: A high D/E ratio is often associated with high investment risk; it means that a company relies primarily on debt financing. If a company has a negative D/E ratio, this means that it has negative shareholder equity. In other words, the company’s liabilities exceed its assets. In most cases, this would be considered a sign of high risk and an incentive to seek bankruptcy protection. | H7: A positive FCFF value indicates that the firm has cash remaining after expenses. | I7: FCFE to determine if dividend payments and stock repurchases are paid for with free cash flow to equity or some other form of financing. Investors want to see a dividend payment and share repurchase that is fully paid by FCFE.
C8: When a working capital calculation is negative, this means the company's current assets are not enough to pay for all of its current liabilities. The company has more short-term debt than it has short-term resources. Negative working capital is an indicator of poor short-term health, low liquidity, and potential problems paying its debt obligations as they become due. | D8: In addition to other financial measures, the CCC value indicates how efficiently a company’s management is using the short-term assets and liabilities to generate and redeploy the cash and gives a peek into the company’s financial health with respect to cash management. The figure also helps assess the liquidity risk linked to a company’s operations. | F8: As a result, companies with a low ROA tend to have more debt since they need to finance the cost of the assets. Having more debt is not bad as long as management uses it effectively to generate earnings.A rising ROA tends to indicate a company is increasing its profits with each investment dollar invested in the company's total assets. A declining ROA may indicate a company might have made poor capital investment decisions and is not generating enough profit to justify the cost of purchasing those assets. A declining ROA could also indicate the company's profits are shrinking due to declining sales or revenue. | G8: Generally speaking, a D/E ratio below 1 would be seen as relatively safe, whereas values of 2 or higher might be considered risky. | H8: A negative value indicates that the firm has not generated enough revenue to cover its costs and investment activities. | I8: If FCFE is less than the dividend payment and the cost to buy back shares, the company is funding with either debt or existing capital or issuing new securities. Existing capital includes retained earnings made in previous periods.

Sheet Funds Flow - 23 Vs 24
B1: Home Index (click here)
A3: B) | B3: Schedule of Changes in Working Capital | D3: (6 Months) (Jan - June 24)
B4: (Difference in Current Assets - Current Liabilities)
B5: (Only CA & CL taken here)
E6: Changes in Working Capital
B7: Statement of Changes in Working Capital | C7: 45291 | D7: 45473 | E7: Increase + | F7: Decrease (-)
A8: I) | B8: Current Assets (Funds Use)
B9: Inventories | C9: =+'FS with Schedules'!I101 -> 69450796 | D9: =+'FS with Schedules'!J101 -> 66180974 | E9: =IF(D9>C9,D9-C9,0) -> 0 | F9: =IF(D9<C9,C9-D9,0) -> 3269822
B10: Trade Receivables | C10: =+'FS with Schedules'!I106 -> 296070720 | D10: =+'FS with Schedules'!J106 -> 263952251 | E10: =IF(D10>C10,D10-C10,0) -> 0 | F10: =IF(D10<C10,C10-D10,0) -> 32118469
B11: Prepayments and other current assets | C11: =+'FS with Schedules'!I113 -> 41736989 | D11: =+'FS with Schedules'!J113 -> 46471122 | E11: =IF(D11>C11,D11-C11,0) -> 4734133 | F11: =IF(D11<C11,C11-D11,0) -> 0
B12: Cash & cash equivalent | C12: =+'FS with Schedules'!I118 -> 11888779 | D12: =+'FS with Schedules'!J118 -> 4163401 | E12: =IF(D12>C12,D12-C12,0) -> 0 | F12: =IF(D12<C12,C12-D12,0) -> 7725378
B14: Total Current Assets (I) | C14: =SUM(C9:C13) -> 419147284 | D14: =SUM(D9:D13) -> 380767748
A16: II) | B16: Current Liabilties (Funds Source)
B17: Trade Payables | C17: =+'FS with Schedules'!I144 -> 107468896 | D17: =+'FS with Schedules'!J144 -> 145228527 | E17: =IF(D17<C17,C17-D17,0) -> 0 | F17: =IF(D17>C17,D17-C17,0) -> 37759631
B18: Due to Related Parties | C18: 12141843 | D18: 0 | E18: =IF(D18<C18,C18-D18,0) -> 12141843 | F18: =IF(D18>C18,D18-C18,0) -> 0
B19: Accruals and other current liabilities | C19: =+'FS with Schedules'!I156-C18 -> 33988154 | D19: =+'FS with Schedules'!J156 -> 30889137 | E19: =IF(D19<C19,C19-D19,0) -> 3099017 | F19: =IF(D19>C19,D19-C19,0) -> 0
B20: Short term loans | C20: =+'FS with Schedules'!I158 -> 267678203 | D20: =+'FS with Schedules'!J158 -> 250163701 | E20: =IF(D20<C20,C20-D20,0) -> 17514502 | F20: =IF(D20>C20,D20-C20,0) -> 0
B21: Current portion of term loans | C21: =+'FS with Schedules'!I160 -> 58946986 | D21: =+'FS with Schedules'!J160 -> 40232391 | E21: =IF(D21<C21,C21-D21,0) -> 18714595 | F21: =IF(D21>C21,D21-C21,0) -> 0
B22: Current portion of lease liabilities | C22: =+'FS with Schedules'!I162 -> 992455 | D22: =+'FS with Schedules'!J162 -> 5544675 | E22: =IF(D22<C22,C22-D22,0) -> 0 | F22: =IF(D22>C22,D22-C22,0) -> 4552220
B23: Zakat Provision | C23: =+'FS with Schedules'!I164 -> 1754223 | D23: =+'FS with Schedules'!J164 -> 1559142 | E23: =IF(D23<C23,C23-D23,0) -> 195081 | F23: =IF(D23>C23,D23-C23,0) -> 0
B25: Total Current Liabilities (II) | C25: =SUM(C17:C23) -> 482970760 | D25: =SUM(D17:D23) -> 473617573
B27: Negative Working Capital (I - II) | C27: =C14-C25 -> -63823476 | D27: =D14-D25 -> -92849825 | E27: =SUM(E9:E24) -> 56399171 | F27: =SUM(F9:F24) -> 85425520
B28: (Funds Sources > Usage Assets)
B29: Net increase of Working Capital | D29: =(D27-C27) -> -29026349 | E29: =E27-F27 -> -29026349
B30: in 2024 for 6 months as on 30 June 24.
A36: A) | B36: Funds from Operations (Adjusted Profit & Loss A/c)
B37: Remove Non-cash / Non-Operating items. (No Investing / Finance Items)
B38: Particulars | C38: Amount | D38: Particulars | E38: Amount | G38: Profit (loss) | H38: =+' - CFS'!J5 -> -28862477
G39: add
D40: By Bal B/d pf PL 2023(Opening Balance) | E40: =+EBITDA!$I$19 -> -107770886 | G40: Deprcn | H40: =643874701-628232899 -> 15641802
B41: ammprtn on intangible assets | C41: =1056775-968632 -> 88143 | G41: intangible | H41: =1056775-968632 -> 88143
B43: employee deem benefits | C43: =49975669-48766362 -> 1209307 | G43: less
G44: employee | H44: =49975669-48766362 -> 1209307
B46: deprcn of PPE | C46: =643874701-628232900 -> 15641801 | G46: cash used in ops | H46: =H38+H40+H41-H67-H44 -> -21180649
B47: sale of vehicles | C47: =21472009-19798779 -> 1673230
B48: reducn in RE | C48: =55612708-26328642 -> 29284066
B49: allowance for inventory slow move | C49: =7979837-7379837 -> 600000
B54: To Bal C/d of PL 2024 (Closing Balance) | C54: =+EBITDA!$J$19 -> -28862477
B56: To Funds Lost in Operations | C56: =$E$59-SUM(C40:C54) -> -127404956 | D56: By Funds Generated from Operations | E56: 0
B57: (Bal Figure) | D57: (Bal Figure)
C59: =E59 -> -107770886 | E59: =SUM(E40:E58) -> -107770886
A62: C) | B62: Funds Flow Statement
B63: (This is like CFS Invst / Fin activities) | C63: (Only Non CA & Non CL taken here) | E63: Not Match with schedule of WC above
B64: Sources of Funds (+) | C64: Amount | D64: Application of Funds (-) | E64: Amount | G64: source | H64: use
H65: =-H46 -> 21180649
G66: =42658456-42621346 -> 37110
B67: Funds from ops | C67: 61419876 | H67: =16605522-9766712 -> 6838810
D68: invst of assoc | E68: =21502182-20664843 -> 837339 | G68: =-D29 -> 29026349
B69: invest property | C69: =42658456-42621346 -> 37110 | D69: equity reduce | E69: 29284066 | H69: =21502182-20664843 -> 837339
D70: loans paid | E70: =69267710-55952059 -> 13315651
B71: emplouee benefit | C71: 1209307 | D71: lease liability | E71: =11479954-7206799 -> 4273155 | H71: =69267710-55952059 -> 13315651
H73: =11479954-7206799 -> 4273155
G75: =SUM(G66:G72) -> 29063459 | H75: =SUM(H65:H73) -> 46445604
H77: =H75-G75 -> 17382145
B78: Funds from Operations (+)
B80: Decrease in Working Capital (+) | D80: Increase in Working Capital (-) | E80: =-+D29 -> 29026349
C82: =SUM(C65:C81) -> 62666293 | E82: =SUM(E65:E81) -> 76736560
E83: =C82-E82 -> -14070267
B84: Conclusion:
B85: # This shows we are investing in long term investments projects without due consideration on our funds
B86: position. AR has to be much more than currently being done.
B87: # Very close Treasury management in alignment with cash flows on a daily/weekly basis.
B88: # This leads to heavy short term borrowing at rates which are higher than our loss rate and adds
B89: up to our cost of product.
B91: Therefore, in conclusion simply put we are bleeding cash, out without cash generation and that will
B92: eventually at year end lead to nil balance in RE and consequently put waraq in a solvency position.
B94: Some measurements which can be to minimize above is:
B95: # Rationalization of recruitment policy
B96: # Rationalization of consultant policy
B97: # Manpower audit to have just optimal employee strength per department
... B102: # Retirement of high cost employees or non-performing employees

Sheet FFS 2024
B2: Funds Flow Statement - Analysis (2024 - 6 months)
B4: Ideal Scenario | H4: W is Diversion of Working Capital (Short Term Surplus) For Long Term Usage as seen.
B5: Sources of Funds (Liability) | E5: Uses of Funds (Assets)
H6: 1) ST has higher cost of funds being used for LT which normally should have lower cost of funds
H7: At moment we have average 9% cost of funds which need to be evaluated against our returns.
B8: Long Term Sources | D8: Long Term Usage
H9: 2) Ideally LT Funds used for ST but we are just doing the opposite and so we are facing WC problems
H10: As currently can be seen we now divert 93m of WC towards long term usage. This is not correct.
D11: Surplus LT Sources > LT Usage
D12: # +ve Working Capital | H12: 3) Evaluate Capex Funding and priotize the same. Evaluate maintenance projects and procurement
D13: LT surplus to fund ST usage | F13: CA > CL
H14: 4) Having ST surplus does not mean we have FCF free cash flows.
B15: Undesired Scenario | C15: W | H15: Simply because ST Surplus is being generated via loans.
B16: Sources of Funds (Liability) | E16: Uses of Funds (Assets) | H16: Though we are on the edge with Operational Surplus 61m (6 monthly) in CFS
H17: But we have to go in depth with our Investments and how we finance them ???
B19: Long Term Sources | C19: =+C28 -> 617080756 | D19: Long Term Usage | F19: =+C30 -> 7.0993058e+08 | H19: 5) We are -ve Free Cash Flows (FCFF) as seen ie -46m . This means we are not able convert
H20: our slim operational surplus into actual profits
H21: This is primarily due to Low Sales Price, Weak AR, weak optimal product mix, capex control and
B22: Deficit LT Sources < LT Usage | H22: other factors.
B23: # -ve Working Capital | C23: =+C40 -> 92849825
B24: ST surplus to fund LT Usage | C24: CA < CL | H24: 6) As thumb rule company need to maintain 3X of WC. Therefore, 3 x 93m = 280m. This is approx
H25: the AR figure if recovered it will be good progress towards re-gain financial health.
B27: Long Term
B28: Sources- Liability | C28: =+'FS with Schedules'!J142+'FS with Schedules'!J129 -> 617080756 | H28: Note:
H29: Ideally LT Surplus should be used for ST Deficit. But w is doing opposite.
B30: Usage - Assets | C30: =+'FS with Schedules'!J91 -> 7.0993058e+08 | H30: Treasury management, AR, Sales Price Discovery, Capex Projects, Consideration of our WACC & IRR
H31: change of ERP, all should be tightly controlled and looked into.
B32: LT Deficit | C32: =C28-C30 -> -92849826
H33: Many areas in CA & CL related to all departments need to be analysed and corrective action be taken.
B35: Short Term | E35: Using Working Capital to fund | H35: Concentrated efforts to form a Waraq Working Capital Policy in line with other policies to be taken up
B36: Sources- Liability (CL) | C36: =+'FS with Schedules'!J166 -> 473617573 | E36: Long Term Usage | H36: on immediate priority. With cross department implementaton.
B37: CA < CL
B38: Usage - Assets (CA) | C38: =+'FS with Schedules'!J120 -> 380767748
B40: ST Surplus | C40: =C36-C38 -> 92849825
B42: Abbreviations:
B43: ST = Short Term (Current < 1 year)
B44: LT = Long Term (Non Current > 1 year)
B45: WC = Working Capital
B46: WACC = Weighted Average Cost of Capital
B47: FCFF = Free Cash Flow to Firm
B48: CFS = Cash Flow Statement
B52: Example: | C52: Not Recommend | D52: Very Bad | E52: Ideal Scenario
C53: A | D53: B (Waraq) | E53: C
B54: Long Term Funds | C54: 50 | D54: 25 | E54: 75
B56: Short Term Funds | C56: 50 | D56: 75 | E56: 25
C58: 100 | D58: 100 | E58: 100
B60: Long Term Assets | C60: 50 | D60: 50 | E60: 50
B62: Short Term Assets | C62: 50 | D62: 50 | E62: 50
C64: 100 | D64: 100 | E64: 100

Sheet WC Calcn
B2: Long Term - Shortage | C2: =C5-C27 -> -92849826
C4: Consolidated | D4: Elimination | E4: W | F4: A | G4: T
B5: Long Term - Sources - Liability | C5: =C11+C16+C20+C22 -> 6.1708075e+08 | D5: IFRS
B7: Share Capital | C7: =SUM(D7:G7) -> 450000000 | D7: -16500000 | E7: 450000000 | F7: 16000000 | G7: 500000
B8: Statutory Reserve | C8: =SUM(D8:G8) -> 23344431 | D8: -1963635 | E8: 23344431 | F8: 1813635 | G8: 150000
B9: General Reserve | C9: =SUM(D9:G9) -> 0 | D9: 0 | E9: 0 | F9: 0 | G9: 0
B10: Retained Earnings / (Accumulated Losses) | C10: =SUM(D10:G10) -> 26328642 | D10: 1515452 | E10: 26328642 | F10: -2756231 | G10: 1240779
B11: Total Equity | C11: =SUM(C7:C10) -> 499673073 | D11: =SUM(D7:D10) -> -16948183 | E11: =SUM(E7:E10) -> 499673073 | F11: =SUM(F7:F10) -> 15057404 | G11: =SUM(G7:G10) -> 1890779
B13: Long Term Loan- RYD Bank | C13: =-SUM(D13:G13) -> 22222222 | D13: 0 | E13: -22222222 | F13: 0 | G13: 0
B14: Long Term Loan - SNB Bank | C14: =-SUM(D14:G14) -> 30595237 | D14: 0 | E14: -30595237 | F14: 0 | G14: 0
B15: Tawaruq Long Term Loans-ANB | C15: =-SUM(D15:G15) -> 3134600 | D15: 0 | E15: 0 | F15: -3134600 | G15: 0
B16: Term Loans | C16: =SUM(C13:C15) -> 55952059 | D16: 0 | E16: =SUM(E13:E15) -> -52817459 | F16: =SUM(F13:F15) -> -3134600 | G16: =SUM(G13:G15) -> 0
B18: Provision for Staff Benefits | C18: =SUM(E18:G18) -> -51677574 | D18: 0 | E18: -34189222 | F18: -4541565.2 | G18: -12946787
B19: Actuarial Remeasurements | C19: =SUM(E19:G19) -> 1701904.7 | D19: 0 | E19: 1267200.7 | F19: -214968.08 | G19: 649672.06
B20: Employees defined benefits liabilities | C20: =-SUM(C18:C19) -> 49975669 | D20: 0 | E20: =SUM(E18:E19) -> -32922021 | F20: =SUM(F18:F19) -> -4756533.3 | G20: =SUM(G18:G19) -> -12297115
B22: Lease Liabilities | C22: =SUM(E22:G22) -> 11479954 | D22: 0 | E22: 11167819 | F22: 312135 | G22: 0
C26: Consolidated | D26: Elimination | E26: W | F26: A | G26: T
B27: Long Term - Usage - Assets | C27: =C56+C60+C64+C68+C72+C74 -> 7.0993058e+08 | D27: IFRS
B28: Land | C28: =SUM(D28:G28) -> 26597909 | D28: 14586811 | E28: 10988040 | F28: 1023058 | G28: 0
B29: Acc Dep | C29: =SUM(D29:G29) -> -9583259.3 | D29: 0 | E29: -9072364.9 | F29: -510894.44 | G29: 0
C30: =SUM(C28:C29) -> 17014650 | D30: =SUM(D28:D29) -> 14586811 | E30: =SUM(E28:E29) -> 1915675 | F30: =SUM(F28:F29) -> 512163.54 | G30: =SUM(G28:G29) -> 0
B32: Buildings & Leasehold Improvements | C32: =SUM(D32:G32) -> 2.2661024e+08 | E32: 2.1967716e+08 | F32: 6933078.7 | G32: 0
B33: Acc Dep | C33: =SUM(D33:G33) -> -1.1919811e+08 | E33: -1.1569572e+08 | F33: -3502381.3 | G33: 0
C34: =SUM(C32:C33) -> 1.0741214e+08 | D34: =SUM(D32:D33) -> 0 | E34: =SUM(E32:E33) -> 1.0398144e+08 | F34: =SUM(F32:F33) -> 3430697.4 | G34: =SUM(G32:G33) -> 0
B36: Plant & Machinery | C36: =SUM(D36:G36) -> 9.7046229e+08 | D36: 0 | E36: 9.4325387e+08 | F36: 27202090 | G36: 6331.5
B37: Acc Dep | C37: =SUM(D37:G37) -> -5.8509762e+08 | D37: 0 | E37: -5.7047544e+08 | F37: -14617889 | G37: -4282.1
C38: =SUM(C36:C37) -> 3.8536468e+08 | D38: =SUM(D36:D37) -> 0 | E38: =SUM(E36:E37) -> 3.7277843e+08 | F38: =SUM(F36:F37) -> 12584201 | G38: =SUM(G36:G37) -> 2049.4
B40: Furniture, Fixtures & Office Equipment | C40: =SUM(D40:G40) -> 33701560 | D40: 0 | E40: 30888920 | F40: 2678508.1 | G40: 134132.35
B41: Acc Dep | C41: =SUM(D41:G41) -> -24714780 | D41: 0 | E41: -22842327 | F41: -1747812.7 | G41: -124640
C42: =SUM(C40:C41) -> 8986780.7 | D42: =SUM(D40:D41) -> 0 | E42: =SUM(E40:E41) -> 8046592.9 | F42: =SUM(F40:F41) -> 930695.45 | G42: =SUM(G40:G41) -> 9492.35
B44: Vehicles | C44: =SUM(D44:G44) -> 58660510 | D44: 0 | E44: 47362407 | F44: 10520159 | G44: 777944
B45: Acc Dep | C45: =SUM(D45:G45) -> -38861731 | D45: 0 | E45: -30746742 | F45: -7906566.3 | G45: -208422.86
C46: =SUM(C44:C45) -> 19798779 | D46: =SUM(D44:D45) -> 0 | E46: =SUM(E44:E45) -> 16615665 | F46: =SUM(F44:F45) -> 2613592.5 | G46: =SUM(G44:G45) -> 569521.14
B48: Capital Work in Progress (CIP) | C48: =SUM(D48:G48) -> 76407651 | D48: 0 | E48: 76407651 | F48: 0 | G48: 0
B49: Acc Dep | C49: =SUM(D49:G49) -> -4670172 | D49: 0 | E49: -4670172 | F49: 0 | G49: 0
C50: =SUM(C48:C49) -> 71737479 | D50: =SUM(D48:D49) -> 0 | E50: =SUM(E48:E49) -> 71737479 | F50: =SUM(F48:F49) -> 0 | G50: =SUM(G48:G49) -> 0
B51: (need to combine CIP + Proj Progress email to Chief Act)
B52: Projects in Progress | C52: =SUM(D52:G52) -> 17918400 | D52: 0 | E52: 10903950 | F52: 7014449.5 | G52: 0
B53: Acc Dep | C53: =SUM(D53:G53) -> 0 | D53: 0 | E53: 0 | F53: 0 | G53: 0
C54: =SUM(C52:C53) -> 17918400 | D54: =SUM(D52:D53) -> 0 | E54: =SUM(E52:E53) -> 10903950 | F54: =SUM(F52:F53) -> 7014449.5 | G54: =SUM(G52:G53) -> 0
B56: Plant Property & Equipment (PP&E) | C56: =C30+C34+C38+C42+C46+C50+C54 -> 6.282329e+08 | D56: =D30+D34+D38+D42+D46+D50+D54 -> 14586811 | E56: =E30+E34+E38+E42+E46+E50+E54 -> 5.8597923e+08 | F56: =F30+F34+F38+F42+F46+F50+F54 -> 27085799 | G56: =G30+G34+G38+G42+G46+G50+G54 -> 581062.89
B58: Right of Use Assets | C58: =SUM(D58:G58) -> 23982180 | D58: -982967 | E58: 17859233 | F58: 7105914 | G58: 0
B59: Acc Dep | C59: =SUM(D59:G59) -> -7566806 | E59: -2917965.7 | F59: -4648840.3 | G59: 0
B60: Right of Use Assets | C60: =SUM(C58:C59) -> 16415374 | D60: =SUM(D58:D59) -> -982967 | E60: =SUM(E58:E59) -> 14941267 | F60: =SUM(F58:F59) -> 2457073.7 | G60: =SUM(G58:G59) -> 0
B62: Intangible Assets | C62: =SUM(D62:G62) -> 4695270.3 | D62: 0 | E62: 4662598.3 | F62: 22672 | G62: 10000
B63: Acc Dep | C63: =SUM(D63:G63) -> -3726638.6 | D63: 0 | E63: -3702967.6 | F63: -22671 | G63: -999.96
B64: Intangible Assets | C64: =SUM(C62:C63) -> 968631.69 | D64: =SUM(D62:D63) -> 0 | E64: =SUM(E62:E63) -> 959630.65 | F64: =SUM(F62:F63) -> 1 | G64: =SUM(G62:G63) -> 9000.04
B66: Investment Properties | C66: =SUM(D66:G66) -> 63145190 | D66: -14586811 | E66: 77732001 | F66: 0 | G66: 0
B67: Acc Dep | C67: =SUM(D67:G67) -> -20523844 | D67: 0 | E67: -20523844 | F67: 0 | G67: 0
B68: Investment Properties | C68: =SUM(C66:C67) -> 42621346 | D68: =SUM(D66:D67) -> -14586811 | E68: =SUM(E66:E67) -> 57208157 | F68: =SUM(F66:F67) -> 0 | G68: =SUM(G66:G67) -> 0
B70: Lease Hold Improvements | C70: =SUM(D70:G70) -> 813391.19 | D70: 0 | E70: 813391.19 | F70: 0 | G70: 0
B71: Acc Dep | C71: =SUM(D71:G71) -> -623242.73 | D71: 0 | E71: -623242.73 | F71: 0 | G71: 0
B72: Lease Hold Improvements | C72: =SUM(C70:C71) -> 190148.46 | D72: =SUM(D70:D71) -> 0 | E72: =SUM(E70:E71) -> 190148.46 | F72: =SUM(F70:F71) -> 0 | G72: =SUM(G70:G71) -> 0
B74: Investment in an associate - East Gas | C74: =SUM(D74:G74) -> 21502182 | D74: 0 | E74: =22226616.11-724434.23 -> 21502182 | F74: 0 | G74: 0
B80: Short Term - Surplus | C80: =C83-C143 -> 92849825
C82: Consolidated | D82: Elimination | E82: W | F82: A | G82: T
B83: Short Term - Sources - Liability | C83: =C91+C98+C102+C107+C132+C138 -> 4.7361757e+08 | D83: IFRS
B85: Short Term Loan - ANB | C85: =SUM(D85:G85) -> 45546967 | E85: 45546967
B86: Short Term Loan-RYD Bank | C86: =SUM(D86:G86) -> 58961796 | E86: 58961796
B87: Short Term Loan-Al-Bilad Bank | C87: =SUM(D87:G87) -> 48946931 | E87: 48946931
B88: Short Term Loan AL-Ahli Bank | C88: =SUM(D88:G88) -> 88889304 | E88: 88889304
B89: Short Term Loan - Refinance ANB | C89: =SUM(D89:G89) -> 2818703 | E89: 2818703
B90: Short Term Loan - ANB | C90: =SUM(D90:G90) -> 5000000 | F90: 5000000
B91: Short Term Loans | C91: =SUM(C85:C90) -> 2.501637e+08 | D91: =SUM(D85:D90) -> 0 | E91: =SUM(E85:E90) -> 2.451637e+08 | F91: =SUM(F85:F90) -> 5000000 | G91: =SUM(G85:G90) -> 0
B93: Tawarruq Loan ANB- Current Portion | C93: =SUM(D93:G93) -> 7503528.4 | D93: 0 | E93: 7503528.4 | G93: 0
B94: Tawarruq Loan - RYD Bank-Current Portion | C94: =SUM(D94:G94) -> 8888888.9 | E94: 8888888.9
B95: Tawarruq Loan Bilad Current Portion | C95: =SUM(D95:G95) -> 6097561.2 | E95: 6097561.2
B96: SNB Long Term Loan - Current Portion | C96: =SUM(D96:G96) -> 11473213 | E96: 11473213
B97: Tawarruq Loan - Current Portion of long term loan | C97: =SUM(D97:G97) -> 6269200 | F97: 6269200
B98: Current Portion Long Term Loans | C98: =SUM(C93:C97) -> 40232391 | D98: 0 | E98: =SUM(E93:E97) -> 33963191 | F98: =SUM(F93:F97) -> 6269200 | G98: =SUM(G93:G97) -> 0
B100: Lease Liability - Current | C100: =SUM(D100:G100) -> 3651270.7 | D100: -1050789 | E100: 4702059.7
B101: Lease Liability - Current | C101: =SUM(E101:G101) -> 1893404.2 | D101: 0 | F101: 1893404.2
B102: Current Portion of Lease Liabilities | C102: =SUM(C100:C101) -> 5544675 | D102: 0 | E102: =SUM(E100:E101) -> 4702059.7 | F102: =SUM(F100:F101) -> 1893404.2 | G102: =SUM(G100:G101) -> 0
B104: Zakat Provision | C104: =SUM(D104:G104) -> 1226676.7 | E104: 1226676.7
B105: Zakat Provision | C105: =SUM(D105:G105) -> 93540.98 | F105: 93540.98
B106: Zakat Provision | C106: =SUM(D106:G106) -> 238924.38 | G106: 238924.38
B107: Provision for Zakat | C107: =SUM(C104:C106) -> 1559142 | D107: =SUM(D104:D106) -> 0 | E107: =SUM(E104:E106) -> 1226676.7 | F107: =SUM(F104:F106) -> 93540.98 | G107: =SUM(G100:G106) -> 238924.38
B109: Other Payables- GOSI | C109: =SUM(D109:G109) -> 683224.22 | E109: 452962.07 | F109: 72502.19 | G109: 157759.96
B110: Other Payables- | C110: =SUM(D110:G110) -> 358609.77 | D110: 67822 | E110: 168405.3 | F110: 122382.47
B111: Accrued Expenses- Elect.&Tel. Post | C111: =SUM(D111:G111) -> 741254.84 | E111: 655560.48 | F111: 85694.36
B112: Accrued Expenes- General | C112: =SUM(D112:G112) -> 6675223.7 | E112: 6362561.8 | G112: 312661.91
B113: Salary Payable | C113: =SUM(D113:G113) -> 1419.53 | E113: -151.38 | F113: 1570.91
B114: Accrued Expenses - Other | C114: =SUM(D114:G114) -> 3364762.9 | E114: 1486456.6 | F114: 1774172.3 | G114: 104134
B115: Provision for Staff Benefits- Tickets | C115: =SUM(D115:G115) -> 1261474.9 | E115: 627836.28 | F115: 259350.02 | G115: 374288.58
B116: Provision for Staff Benefits- Vacation Salary | C116: =SUM(D116:G116) -> 4985107.1 | E116: 3181703 | F116: 644918.87 | G116: 1158485.3
B117: Dues To Employees | C117: =SUM(D117:G117) -> 31525.57 | E117: 31525.57
B118: Accrued For Tax | C118: =SUM(D118:G118) -> 1565675.6 | E118: 1565675.6
B119: Corporate Social Responsibility Fund | C119: =SUM(D119:G119) -> 2011248.8 | E119: 2011248.8
B120: Customer Advances | C120: =SUM(D120:G120) -> 7321081.3 | E120: 7258747 | G120: 62334.24
B121: Customer Advances - VAT | C121: =SUM(D121:G121) -> 454180.68 | E121: 454180.68
B122: HR Penalties | C122: =SUM(D122:G122) -> 1672.44 | E122: 1672.44
B123: Proposed Dividend | C123: =SUM(D123:G123) -> 11475 | E123: 11475
B124: Accrued Loan Commission-ANB PM3 | C124: =SUM(D124:G124) -> 227158.61 | E124: 202233.76 | F124: 24924.85
B125: Accrued Loan Commission-RYD Bank | C125: =SUM(D125:G125) -> 180757.42 | E125: 180757.42
B126: Accrued Loan Commission-ANB | C126: =SUM(D126:G126) -> 221353.42 | E126: 197038.81 | F126: 24314.61
B127: Accrued Loan Commission-BILAD | C127: =SUM(D127:G127) -> 149815.8 | E127: 149815.8
B128: Accrued Loan Commission-NCB | C128: =SUM(D128:G128) -> 324094.38 | E128: 324094.38
B129: Accrued Loan Commission-LTL BILAD | C129: =SUM(D129:G129) -> 1818.14 | E129: 1818.14
B130: Accrued Loan Commission- LTL Riyadh Bank | C130: =SUM(D130:G130) -> 182714.24 | E130: 182714.24
B131: SNB – LTL ACCRUED LOAN COMMISSION | C131: =SUM(D131:G131) -> 133488.18 | E131: 133488.18
...

Sheet Flash Report CFO Dashboard
B1: Home Index (click here)
B3: Working Capital | C3: KPIs | D3: Forecast Vs Actual Vs Benchmark | E3: DSO / DIO / DPO
E4: Working Capital as a % of Sales
E5: DSO + DIO - DPO
C7: Accounts Receivable | D7: Overdue | E7: SAR total balance of overdue accounts
E8: % accounts overdue for collection
D10: Terms | E10: average terms per client/unit/region
E11: % clients with payment term exceptions
D13: Invoicing | E13: Invoicing number of delay days vs. standard
C15: Accounts Payable | D15: Overdue | E15: SAR total balance of overdue accounts
E16: % accounts overdue for payment
D18: Terms | E18: average terms per client/unit/region
E19: % suppliers with payment term exceptions
D21: Processing | E21: % of accounts paid early
E22: SAR total value of payments made early
C24: Inventory | D24: Forecast vs. Actual | E24: SAR inventory balances by type (raw/WIP/FG/transit)
D25: Obsolete | E25: SAR inventory balances written off
D26: At Risk | E26: SAR inventory balances with ptential to be written off
B28: Expenditures | C28: Capex | D28: Actual Vs Forecast | E28: SAR total spend vs. plan
E29: Capex as % of revenue over time
C31: COGS | E31: SAR total spend vs. plan
E32: COGS total as % of revenue over time
C34: OPEX | E34: SAR total spend vs. plan
E35: OPEX categories as % of revenue over time
E36: (SG&A, R&D, Sales, Marketing)
B38: Financial Health | C38: Liquidty | D38: Actual Vs Benchmark | E38: Current Ratio
E39: Quick Ratio (for manufacturers)
C41: Leverage | E41: Total Liabilities to Net Worth
E42: Funded Debt to EBITDA
C44: Debt Servicing | E44: Fixed Charge Coverage Ratio
E45: EBITDA/Interest (if no term debt)
C47: EBITDA | E47: Current and Rolling 12 month EBITDA | J47: Based on Budget
E48: Management Adjusted EBITDA (if applicable)
C50: Cash Flows | E50: Operating Cash Flow
E51: Investing Cash Flow
E52: Financing Cash Flow
E53: Free Cash Flow to Firm FCFF
B55: Flash Report | C55: ????
B56: Profitability | C56: Productivity | D56: Liquidity / Cash Flows
B58: Profit Margin | C58: Fixed Assets T/o | D58: Operating CF / Sales Ratio
B59: Gross Margin | C59: Sales Rev / Employee | D59: FCF / Operating Cash Flow
B60: Effective Tax Rate | C60: Operating Cycle | D60: Cash Flow Coverage Ratio
B61: Return on Assets | C61: CCC | D61: Capitalization Ratio
B62: Return on Equity | C62: A/R T/o | D62: Cash Flow to Debt Ratio
B63: Du Point | C63: A/P T/o
B64: Return on Capital Employed | C64: Investment T/o

Sheet Projections
B1: Home Index (click here)
B3: Exponential Triple Smoothing for Sales Projections: (ETS)
B4: This is a statistical technique in excel to predict future sales based on historical performance.

Sheet Old Funds Flow (incorrect)
B1: Home Index (click here)
A3: A) | B3: Funds from Operations (Adjusted Profit & Loss A/c)
B5: Particulars | C5: Amount | D5: Particulars | E5: Amount
B7: To Depreciation (Decrease in PPE) | C7: ='FS with Schedules'!$I$79-'FS with Schedules'!$J$79 -> 15641801 | D7: By Bal B/d pf PL 2023(Opening Balance) | E7: =+EBITDA!$I$19 -> -107770886
B9: To Intangible Assets (Decrease Deprcn) | C9: ='FS with Schedules'!$I$83-'FS with Schedules'!$J$83 -> 88143
B11: To Decrease in Capital A/c (Loss)
B12: (Reduction in Retained Earnings)
B14: To Employee Deemed Benefit (Incr) | C14: ='FS with Schedules'!$J$138-'FS with Schedules'!$I$138 -> 1209307
B16: To Bal C/d of PL 2024 (Closing Balance) | C16: =+EBITDA!$J$19 -> -28862477
B18: To Funds Lost in Operations | C18: =$E$21-SUM(C7:C16) -> -95847660 | D18: By Funds from Operations | E18: 0
B19: (Bal Figure) | D19: (Bal Figure)
C21: =E21 -> -107770886 | E21: =SUM(E7:E20) -> -107770886
A23: B) | B23: Schedule of Changes in Working Capital | D23: (6 Months) (Jan - June 24)
B24: (Difference in Current Assets - Current Liabilities)
B25: (Only CA & CL taken here)
E26: Changes in Working Capital
B27: Statement of Changes in Working Capital | C27: 45291 | D27: 45473 | E27: Increase + | F27: Decrease (-)
A28: I) | B28: Current Assets
B29: Inventories | C29: =+'FS with Schedules'!I101 -> 69450796 | D29: =+'FS with Schedules'!J101 -> 66180974 | E29: =IF(D29>C29,D29-C29,0) -> 0 | F29: =IF(D29<C29,C29-D29,0) -> 3269822
B30: Trade Receivables | C30: =+'FS with Schedules'!I106 -> 296070720 | D30: =+'FS with Schedules'!J106 -> 263952251 | E30: =IF(D30>C30,D30-C30,0) -> 0 | F30: =IF(D30<C30,C30-D30,0) -> 32118469
B31: Prepayments and other current assets | C31: =+'FS with Schedules'!I113 -> 41736989 | D31: =+'FS with Schedules'!J113 -> 46471122 | E31: =IF(D31>C31,D31-C31,0) -> 4734133 | F31: =IF(D31<C31,C31-D31,0) -> 0
B32: Cash & cash equivalent | C32: =+'FS with Schedules'!I118 -> 11888779 | D32: =+'FS with Schedules'!J118 -> 4163401 | E32: =IF(D32>C32,D32-C32,0) -> 0 | F32: =IF(D32<C32,C32-D32,0) -> 7725378
B34: Total Current Assets (I) | C34: =SUM(C29:C33) -> 419147284 | D34: =SUM(D29:D33) -> 380767748
A36: II) | B36: Current Liabilties
B37: Trade Payables | C37: =+'FS with Schedules'!I144 -> 107468896 | D37: =+'FS with Schedules'!J144 -> 145228527 | E37: =IF(D37<C37,C37-D37,0) -> 0 | F37: =IF(D37>C37,D37-C37,0) -> 37759631
B38: Due to Related Parties | C38: 12141843 | D38: 0 | E38: =IF(D38<C38,C38-D38,0) -> 12141843 | F38: =IF(D38>C38,D38-C38,0) -> 0
B39: Accruals and other current liabilities | C39: =+'FS with Schedules'!I156 -> 46129997 | D39: =+'FS with Schedules'!J156 -> 30889137 | E39: =IF(D39<C39,C39-D39,0) -> 15240860 | F39: =IF(D39>C39,D39-C39,0) -> 0
B40: Short term loans | C40: =+'FS with Schedules'!I158 -> 267678203 | D40: =+'FS with Schedules'!J158 -> 250163701 | E40: =IF(D40<C40,C40-D40,0) -> 17514502 | F40: =IF(D40>C40,D40-C40,0) -> 0
B41: Current portion of term loans | C41: =+'FS with Schedules'!I160 -> 58946986 | D41: =+'FS with Schedules'!J160 -> 40232391 | E41: =IF(D41<C41,C41-D41,0) -> 18714595 | F41: =IF(D41>C41,D41-C41,0) -> 0
B42: Current portion of lease liabilities | C42: =+'FS with Schedules'!I162 -> 992455 | D42: =+'FS with Schedules'!J162 -> 5544675 | E42: =IF(D42<C42,C42-D42,0) -> 0 | F42: =IF(D42>C42,D42-C42,0) -> 4552220
B43: Zakat Provision | C43: =+'FS with Schedules'!I164 -> 1754223 | D43: =+'FS with Schedules'!J164 -> 1559142 | E43: =IF(D43<C43,C43-D43,0) -> 195081 | F43: =IF(D43>C43,D43-C43,0) -> 0
B45: Total Current Liabilities (II) | C45: =SUM(C37:C43) -> 495112603 | D45: =SUM(D37:D43) -> 473617573
B47: Working Capital (I - II) | C47: =C34-C45 -> -75965319 | D47: =D34-D45 -> -92849825 | E47: =SUM(E29:E44) -> 68541014 | F47: =SUM(F29:F44) -> 85425520
B49: Net decrease (deficit) of Working Capital | D49: =(D47-C47) -> -16884506 | E49: =E47-F47 -> -16884506
B50: in 2024 for 6 months as on 30 June 24.
A61: C) | B61: Funds Flow Statement
B62: (This is like CFS Invst / Fin activities) | C62: (Only Non CA & Non CL taken here) | E62: Not Balance
B63: Sources of Funds (+) | C63: Amount | D63: Application of Funds (-) | E63: Amount
B65: Decrease in Investment Properties | C65: ='FS with Schedules'!$I$85-'FS with Schedules'!$J$85 -> 37110 | D65: Increase in Right of Use Assets | E65: ='FS with Schedules'!$J$81-'FS with Schedules'!$I$81 -> 6648662
B67: Increase in Lease Liability | C67: ='FS with Schedules'!$J$140-'FS with Schedules'!$I$140 -> 4273155 | D67: Increase in Lease Hold Improvements | E67: ='FS with Schedules'!$J$87-'FS with Schedules'!$I$87 -> 190148
D69: Increase in Investment of Associate | E69: ='FS with Schedules'!$J$89-'FS with Schedules'!$I$89 -> 837339
D71: Decrease in Term Loans | E71: ='FS with Schedules'!$I$135-'FS with Schedules'!$J$135 -> 13315651
B73: Funds from Operations (+) | C73: 0 | D73: Funds lost in Operations (-) | E73: =+$C$18 -> -95847660
B75: Decrease in Working Capital (+) | C75: 0 | D75: Increase in Working Capital (-) | E75: =+$E$49 -> -16884506
C77: =SUM(C64:C76) -> 4310265 | E77: =SUM(E64:E76) -> -91740366
E78: =C77-E77 -> 96050631
